Workbook
Name Dépenses_Courantes: Config!$L$2:$L$5
Name Entretien_Espaces_Verts: Config!$O$2:$O$5
Name Journal_Types: Config!$H$2:$H$7
Name ModesRecette: Tableau2[Mode Recette]
Name ModesRecette: Tableau2[Mode Recette]
Name Paie___Primes___CNSS: Config!$J$2:$J$5
Name Téléphonie___Electricité: Config!$K$2:$K$5
Name Transfert: Config!$M$2:$M$5
Name Travaux: Config!$N$2:$N$5

Sheet 2022
D1: Espèce
D2: Chèque
D3: Virement
F4: SITUATION DES COTISATIONS
M5: Immeuble | N5: 1
M6: Année | N6: 2022
A7: Apprt | B7: Copropriétaire | C7: Janvier | D7: Février | E7: Mars | F7: Avril | G7: Mai | H7: Juin | I7: Juillet | J7: Aout | K7: Septembre | L7: Octobre | M7: Novembre | N7: Décembre | O7: Garage | P7: Total | Q7: Remarques
A8: 1 | B8: LAHRAS YOUNES | C8: PAYE | D8: 260 | E8: 260 | F8: PAYE | G8: 390 | H8: PAYE | I8: 390 | J8: PAYE | L8: PAYE | M8: 260 | N8: 260 | P8: =SUM(C8:O8) -> 1820
A9: 2 | B9: YABOURI MED | C9: PAYE | E9: 560 | F9: 140 | G9: PAYE | H9: PAYE | I9: 280 | J9: PAYE | L9: 280 | M9: PAYE | N9: 420 | P9: =SUM(C9:O9) -> 1680
A10: 3 | B10: EL BAKKALI IDRISSI | C10: PAYE | I10: 2000 | J10: PAYE | P10: =SUM(C10:O10) -> 2000
A11: 4 | B11: BALBOUL LAHCEN | C11: PAYE | D11: 140 | E11: 140 | F11: 140 | G11: 140 | H11: 140 | I11: 140 | J11: 140 | K11: 140 | L11: 280 | M11: PAYE | N11: 280 | P11: =SUM(C11:O11) -> 1680
A12: 5 | B12: IDRISSI MOKHTAR | C12: PAYE | D12: PAYE | E12: 280 | F12: 280 | G12: 140 | H12: 280 | I12: 140 | J12: 140 | K12: 140 | L12: 280 | M12: 140 | N12: 280 | P12: =SUM(C12:O12) -> 2100
A13: 6 | B13: HICHAM MANSOUR | C13: PAYE | M13: 1680 | N13: PAYE | P13: =SUM(C13:O13) -> 1680
A14: 7 | B14: BENJELLOUN AMINE | C14: 130 | D14: 130 | E14: 130 | F14: PAYE | G14: 260 | H14: 130 | I14: 130 | J14: PAYE | K14: 260 | L14: 130 | M14: 130 | N14: PAYE | P14: =SUM(C14:O14) -> 1430
A15: 8 | B15: CHERKAOUI MOHAMED | C15: 140 | D15: PAYE | F15: 280 | G15: 140 | H15: 140 | I15: PAYE | J15: 140 | K15: 280 | L15: 140 | M15: 140 | N15: 140 | P15: =SUM(C15:O15) -> 1540
A16: 9 | B16: HIMDI FAROUK | C16: 140 | D16: PAYE | E16: 280 | F16: 140 | G16: 140 | H16: PAYE | J16: 280 | K16: 140 | L16: 140 | M16: PAYE | P16: =SUM(C16:O16) -> 1260
A17: 10 | B17: BENHAMMOU MOHAMED | C17: PAYE | D17: 140 | E17: 280 | F17: PAYE | G17: 140 | H17: PAYE | I17: 280 | J17: 140 | K17: 140 | L17: 140 | M17: 140 | N17: 140 | P17: =SUM(C17:O17) -> 1540
A18: 11 | B18: BOUFOUS KHALID | C18: PAYE | H18: 780 | I18: PAYE | M18: 1430 | N18: PAYE | P18: =SUM(C18:O18) -> 2210 | Q18: 1er semestre 2022 payé le 13/12/2021
A19: 12 | B19: EL OUARCHITI MOHAMED | C19: PAYE | F19: 840 | G19: PAYE | I19: PAYE | K19: 840 | L19: PAYE | P19: =SUM(C19:O19) -> 1680
A20: 13 | B20: BENKARACHE | C20: 280 | D20: PAYE | E20: 280 | F20: 280 | G20: PAYE | H20: 280 | I20: PAYE | K20: 140 | L20: 280 | M20: PAYE | N20: 280 | P20: =SUM(C20:O20) -> 1820
A21: 14 | B21: MME CHERKAOUI | C21: PAYE | P21: =SUM(C21:O21) -> 0
A22: 15 | B22: ALOUI LHOUCINE | C22: PAYE | D22: 130 | E22: 130 | F22: 130 | G22: 130 | H22: 130 | I22: 130 | J22: 130 | K22: 130 | L22: 260 | M22: PAYE | N22: 130 | P22: =SUM(C22:O22) -> 1430
A23: 16 | B23: LATRACH | C23: 140 | D23: 140 | E23: 140 | F23: 140 | G23: 140 | H23: 140 | I23: 140 | J23: 140 | K23: 140 | L23: 140 | M23: 140 | N23: 280 | P23: =SUM(C23:O23) -> 1820
A24: 17 | B24: LAZRAK | C24: 140 | D24: 140 | E24: 140 | F24: 140 | G24: 140 | H24: 140 | I24: 140 | J24: 140 | K24: 140 | L24: 140 | M24: 140 | N24: 140 | P24: =SUM(C24:O24) -> 1680
A25: 18 | B25: KEZZOULI ABDELGHANI | C25: PAYE | H25: 1680 | I25: PAYE | P25: =SUM(C25:O25) -> 1680
A26: 19 | B26: YOUSFI SANAE | C26: 520 | D26: PAYE | K26: 130 | L26: 910 | M26: PAYE | P26: =SUM(C26:O26) -> 1560
A27: 20 | B27: CHBANI KACEM | C27: 560 | D27: PAYE | H27: 840 | I27: PAYE | N27: 840 | P27: =SUM(C27:O27) -> 2240
A28: Total | C28: =SUM(C8:C27) -> 2050 | D28: =SUM(D8:D27) -> 1080 | E28: =SUM(E8:E27) -> 2620 | F28: =SUM(F8:F27) -> 2510 | G28: =SUM(G8:G27) -> 1760 | H28: =SUM(H8:H27) -> 4680 | I28: =SUM(I8:I27) -> 3770 | J28: =SUM(J8:J27) -> 1250 | ... P28: =SUM(P8:P27) -> 32850
F30: SITUATION DES COTISATIONS
M31: Immeuble | N31: 2
M32: Année | N32: 2022
A33: Apprt | B33: Copropriétaire | C33: Janvier | D33: Février | E33: Mars | F33: Avril | G33: Mai | H33: Juin | I33: Juillet | J33: Aout | K33: Septembre | L33: Octobre | M33: Novembre | N33: Décembre | O33: Garage | P33: Total | Q33: Remarques
A34: 1 | B34: ASKAOUI | C34: 140 | D34: 140 | E34: 140 | F34: 140 | G34: 140 | H34: 140 | I34: 280 | J34: 280 | K34: PAYE | L34: 280 | M34: 140 | N34: 140 | P34: =SUM(C34:O34) -> 1960
A35: 2 | B35: MELLOUKI | C35: PAYE | E35: 840 | F35: PAYE | L35: 100 | P35: =SUM(C35:O35) -> 940
A36: 3 | B36: BOURAS | C36: PAYE | E36: 1260 | F36: PAYE | K36: 1120 | P36: =SUM(D36:O36) -> 2380 | Q36: Barid Bank say N°3585484 du 20/08/22
A37: 4 | B37: ABDESSADEK | C37: 560 | D37: PAYE | E37: 280 | F37: PAYE | G37: 280 | H37: PAYE | I37: 280 | J37: 140 | K37: 140 | L37: 280 | M37: PAYE | P37: =SUM(C37:O37) -> 1960 | Q37: paiement efféctué le 09/02/2023
A38: 5 | B38: MME BOUAYAD | C38: 280 | D38: PAYE | E38: 140 | F38: 280 | G38: 140 | H38: 140 | I38: 140 | J38: 280 | K38: 140 | L38: 140 | M38: 140 | N38: 140 | P38: =SUM(C38:O38) -> 1960
A39: 6 | B39: TOK HASSAN | C39: PAYE | E39: PAYE | H39: 280 | I39: PAYE | O39: PAYE | P39: =SUM(C39:O39) -> 280 | Q39: paiement efféctué le 16/03/2023
A40: 7 | B40: BELFKIH MUSTAFA | C40: 420 | D40: PAYE | E40: 280 | F40: PAYE | H40: 560 | I40: PAYE | J40: 280 | K40: PAYE | N40: 560 | P40: =SUM(C40:O40) -> 2100
A41: 8 | B41: OUHNAOUI MOHAMED | C41: PAYE | D41: 1680 | E41: PAYE | J41: 840 | K41: PAYE | P41: =SUM(D41:O41) -> 2520 | Q41: chèqueBP coc N° 7439562 du 23/01/23
A42: 9 | B42: BOURI | C42: PAYE | E42: 1400 | F42: PAYE | K42: 1120 | L42: PAYE | P42: =SUM(C42:O42) -> 2520 | Q42: Barid Bank say N°3585484 du 20/08/22
A43: 10 | B43: MERNISSI | C43: PAYE | E43: 1400 | F43: PAYE | J43: 420 | K43: PAYE | P43: =SUM(C43:O43) -> 1820
A44: 11 | B44: DIOURI ABBES | C44: PAYE | D44: 840 | E44: PAYE | I44: 840 | J44: PAYE | N44: 840 | O44: 50 | P44: =SUM(C44:O44) -> 2570
A45: 12 | B45: MAADAD ABDELKADER | C45: PAYE | H45: 1680 | I45: PAYE | O45: 50 | P45: =SUM(C45:O45) -> 1730 | Q45: chèque Attijari n°546134 DU 01/06/22
A46: 13 | B46: ETTAZI | C46: PAYE | I46: 900 | J46: PAYE | O46: PAYE | P46: =SUM(C46:O46) -> 900 | Q46: BP CPB 2757062(24/12/21) & 063(27/7/22)
A47: 14 | B47: HADDOUCHI | C47: PAYE | F47: 1680 | G47: PAYE | O47: 50 | P47: =SUM(C47:O47) -> 1730 | Q47: BMCI MFC n°4447565
A48: 15 | B48: EL KMITI | C48: 140 | D48: PAYE | F48: 280 | G48: 280 | H48: 140 | I48: 140 | J48: 280 | K48: 140 | L48: 140 | M48: 140 | N48: 140 | O48: PAYE | P48: =SUM(C48:O48) -> 1820
A49: 16 | B49: BENABDESLAM AHMED | C49: PAYE | D49: 900 | E49: PAYE | I49: 900 | J49: PAYE | O49: 50 | P49: =SUM(C49:O49) -> 1850 | Q49: CIH,PVC 2401674 (10/2/22)&676 (5/7/22)
A50: 17 | B50: LAASOULI (HERITIERS) | C50: PAYE | E50: PAYE | I50: 600 | J50: PAYE | L50: 1050 | M50: PAYE | O50: PAYE | P50: =SUM(C50:O50) -> 1650
A51: Total | C51: =SUM(C31:C50) -> 1540 | D51: =SUM(D31:D50) -> 3560 | E51: =SUM(E31:E50) -> 5740 | F51: =SUM(F31:F50) -> 2380 | G51: =SUM(G31:G50) -> 840 | H51: =SUM(H31:H50) -> 2940 | I51: =SUM(I31:I50) -> 4080 | J51: =SUM(J31:J50) -> 2520 | ... N51: =SUM(N31:N50) -> 3844 | P51: =SUM(P34:P50) -> 30690
F54: SITUATION DES COTISATIONS
M55: Immeuble | N55: 3
M56: Année | N56: 2022
A57: Apprt | B57: Copropriétaire | C57: Janvier | D57: Février | E57: Mars | F57: Avril | G57: Mai | H57: Juin | I57: Juillet | J57: Aout | K57: Septembre | L57: Octobre | M57: Novembre | N57: Décembre | O57: Garage | P57: Total | Q57: Remarques
A58: 1 | B58: BERKA (HERITIERS) | C58: 130 | D58: 260 | F58: 130 | G58: PAYE | H58: 260 | I58: 130 | J58: PAYE | L58: 390 | M58: PAYE | P58: =SUM(C58:O58) -> 1300 | Q58: paiement efféctué le 31/01/2023
A59: 2 | B59: HAMMOUTAHAR AHMED | C59: PAYE | G59: 700 | H59: PAYE | L59: 700 | M59: PAYE | N59: PAYE | P59: =SUM(C59:O59) -> 1400
A60: 3 | B60: ALAOUI ALI | C60: PAYE | D60: 260 | E60: PAYE | G60: 390 | H60: 130 | I60: 130 | J60: PAYE | K60: PAYE | L60: PAYE | N60: PAYE | P60: =SUM(C60:O60) -> 910
A61: 5 | B61: QELAI | C61: PAYE | I61: 910 | J61: PAYE | P61: =SUM(C61:O61) -> 910
A62: 6 | B62: OUCHRAE | E62: 910 | F62: PAYE | P62: =SUM(C62:O62) -> 910 | Q62: paiement efféctué le 13/02/2023
A63: 7 | B63: AOURARH LHOUCINE | C63: 130 | D63: 130 | E63: 130 | F63: 130 | G63: 130 | H63: 130 | I63: 130 | J63: 130 | K63: 130 | L63: 130 | M63: 130 | N63: 130 | P63: =SUM(C63:O63) -> 1560
A64: 8 | B64: BENJELLOUN | C64: 140 | D64: 140 | E64: 140 | F64: 140 | G64: 140 | H64: 140 | I64: 140 | J64: 140 | K64: 140 | L64: 140 | M64: 140 | N64: PAYE | P64: =SUM(C64:O64) -> 1540
A65: 9 | B65: HAYARI MOHAMED | C65: PAYE | E65: 390 | F65: PAYE | G65: 260 | H65: PAYE | I65: 260 | J65: PAYE | K65: 260 | L65: PAYE | P65: =SUM(C65:O65) -> 1170 | Q65: paiement efféctué le 27/02/2023
A66: 10 | B66: GHISSASSI | C66: PAYE | F66: 1560 | G66: PAYE | P66: =SUM(C66:O66) -> 1560
A67: 11 | B67: IBRAHIMI | C67: PAYE | I67: 1560 | J67: PAYE | P67: =SUM(C67:O67) -> 1560
A68: 12 | B68: ALAOUI | C68: PAYE | L68: 1680 | M68: PAYE | P68: =SUM(C68:O68) -> 1680
A69: 13 | B69: KABILA | C69: PAYE | D69: 260 | E69: PAYE | F69: 260 | G69: PAYE | H69: 260 | I69: PAYE | J69: 260 | K69: PAYE | L69: 260 | M69: PAYE | N69: 260 | P69: =SUM(C69:O69) -> 1560
A70: 14 | B70: MOUSSAOUI | C70: PAYE | J70: 3380 | K70: PAYE | P70: =SUM(C70:O70) -> 3380 | Q70: novembre 21 à fin 2023 (23/08/2022)
A71: 15 | B71: YASSINE | C71: PAYE | D71: 1560 | E71: PAYE | P71: =SUM(C71:O71) -> 1560
A72: 16 | B72: BOUSFIHA (HERITIERS) | C72: PAYE | E72: 980 | F72: PAYE | L72: 1260 | M72: PAYE | P72: =SUM(C72:O72) -> 2240
A73: 17 | B73: SANJARI | C73: PAYE | H73: 780 | I73: PAYE | M73: 780 | N73: PAYE | P73: =SUM(C73:O73) -> 1560
A74: 18 | B74: BERICHE FATIMA | C74: PAYE | D74: 390 | E74: PAYE | F74: PAYE | G74: 390 | H74: PAYE | I74: 390 | J74: PAYE | L74: 390 | M74: PAYE | P74: =SUM(C74:O74) -> 1560
A75: 19 | B75: BENNIS ASSIA | C75: PAYE | E75: 1040 | F75: PAYE | L75: 910 | M75: PAYE | P75: =SUM(C75:O75) -> 1950 | Q75: novbre & décbre 2022 payés le 24/07/23
A76: 20 | B76: EL YOUBI | C76: PAYE | F76: 1120 | G76: PAYE | P76: =SUM(C76:O76) -> 1120
A77: Total | C77: =SUM(C57:C76) -> 400 | D77: =SUM(D57:D76) -> 3000 | E77: =SUM(E57:E76) -> 3590 | F77: =SUM(F57:F76) -> 3340 | G77: =SUM(G57:G76) -> 2010 | H77: =SUM(H57:H76) -> 1700 | I77: =SUM(I57:I76) -> 3650 | J77: =SUM(J57:J76) -> 3910 | ... N77: =SUM(N57:N76) -> 390 | P77: =SUM(P58:P76) -> 29430
F79: SITUATION DES COTISATIONS
M80: Immeuble | N80: 4
M81: Année | N81: 2022
A82: Apprt | B82: Copropriétaire | C82: Janvier | D82: Février | E82: Mars | F82: Avril | G82: Mai | H82: Juin | I82: Juillet | J82: Aout | K82: Septembre | L82: Octobre | M82: Novembre | N82: Décembre | O82: Garage | P82: Total | Q82: Remarques
A83: 1 | B83: TIBRI/MANTEK | C83: PAYE | H83: 1020 | I83: PAYE | J83: 260 | K83: PAYE | M83: 390 | N83: PAYE | P83: =SUM(D83:O83) -> 1670
A84: 2 | B84: AANOUZ SAID | C84: 420 | D84: PAYE | G84: 1680 | H84: PAYE | P84: =SUM(C84:O84) -> 2100
A85: 3 | B85: EL ALAMI ABDELKADER | C85: PAYE | D85: 140 | E85: 140 | F85: 140 | G85: 140 | H85: 280 | I85: PAYE | J85: 140 | K85: PAYE | L85: 140 | M85: PAYE | P85: =SUM(C85:O85) -> 1120 | Q85: paiement efféctué le 01/03/2023
A86: 4 | B86: EL GHOULI (HERITIERS) | C86: PAYE | F86: 640 | G86: PAYE | H86: 280 | I86: PAYE | K86: 560 | L86: PAYE | O86: PAYE | P86: =SUM(C86:O86) -> 1480
A87: 5 | B87: TAMIM AHMED | C87: PAYE | H87: 1680 | I87: PAYE | P87: =SUM(C87:O87) -> 1680
A88: 6 | B88: LAHMANI | C88: 420 | D88: PAYE | F88: 420 | G88: PAYE | I88: 420 | J88: PAYE | L88: 420 | M88: PAYE | P88: =SUM(C88:O88) -> 1680 | Q88: compte BP
A89: 7 | B89: BOUKRAA | C89: PAYE | D89: 1170 | E89: PAYE | K89: 1170 | L89: PAYE
B90: location Garage Syndic | C90: PAYE | K90: 3150 | L90: PAYE | O90: 100 | P90: =SUM(D90:O90) -> 3250
A91: 8 | B91: EL ALAMI MOHAMED | C91: PAYE | D91: 140 | E91: 140 | F91: PAYE | G91: 140 | H91: 140 | I91: 140 | J91: PAYE | K91: 280 | L91: PAYE | N91: 280 | P91: =SUM(C91:O91) -> 1260
A92: 9 | B92: LAHMIDI MOHAMED | C92: 140 | D92: 280 | E92: PAYE | F92: 140 | G92: 280 | H92: PAYE | I92: 140 | J92: 140 | K92: PAYE | L92: 140 | M92: PAYE | N92: 140 | P92: =SUM(C92:O92) -> 1400
A93: 10 | B93: RAMZI (HERITIERS) | P93: =SUM(C93:O93) -> 0
A94: 11 | B94: TIDAF MILOUD | C94: 130 | D94: 130 | E94: 130 | F94: 130 | G94: 130 | H94: 130 | I94: 130 | J94: 130 | K94: 130 | L94: 130 | M94: 130 | N94: 130 | P94: =SUM(C94:O94) -> 1560
A95: 12 | B95: NAHAL BACHIR | C95: PAYE | E95: 420 | F95: PAYE | G95: 420 | H95: PAYE | J95: 420 | K95: PAYE | L95: 420 | M95: PAYE | N95: PAYE | P95: =SUM(C95:O95) -> 1680
A96: 13 | B96: EL FREM TAHAR | C96: PAYE | D96: 1680 | E96: PAYE | P96: =SUM(C96:O96) -> 1680
A97: 14 | B97: SEBBANE MOHAMED | C97: 140 | D97: 140 | E97: 140 | F97: PAYE | G97: 140 | H97: 280 | I97: 140 | J97: 140 | K97: PAYE | L97: 140 | M97: PAYE | N97: 280 | P97: =SUM(C97:O97) -> 1540
A98: 15 | B98: NAFIE MOHAMED | C98: PAYE | E98: 780 | F98: PAYE | H98: 390 | I98: PAYE | K98: 390 | L98: PAYE | N98: 390 | P98: =SUM(C98:O98) -> 1950
A99: 16 | B99: AIT DAHI SAID | C99: PAYE | D99: 140 | E99: 280 | F99: 140 | G99: 140 | H99: 140 | I99: 140 | J99: PAYE | K99: 140 | L99: 140 | M99: 140 | N99: 140 | P99: =SUM(C99:O99) -> 1540
A100: 17 | B100: BOUOUD AHMED | C100: PAYE | D100: 420 | E100: PAYE | H100: 420 | I100: PAYE | M100: 420 | N100: PAYE | P100: =SUM(C100:O100) -> 1260
A101: 18 | B101: ATMANE MOHAMED | C101: 420 | D101: PAYE | F101: PAYE | H101: 420 | I101: PAYE | J101: 420 | K101: PAYE | L101: 420 | M101: PAYE | P101: =SUM(C101:O101) -> 1680
A102: 19 | B102: EL FILALI KHADIJA | C102: 130 | D102: PAYE | E102: 130 | F102: 260 | G102: 130 | H102: PAYE | I102: 130 | J102: 130 | K102: 130 | L102: 130 | M102: PAYE | N102: 130 | P102: =SUM(C102:O102) -> 1300
A103: 20 | B103: OUDGHIRI NOUZHA | C103: 840 | D103: PAYE | J103: 840 | K103: PAYE | P103: =SUM(C103:O103) -> 1680 | Q103: compte BP
A104: Total | C104: =SUM(C83:C103) -> 2640 | D104: =SUM(D83:D103) -> 4240 | E104: =SUM(E83:E103) -> 2160 | F104: =SUM(F83:F103) -> 1870 | G104: =SUM(G83:G103) -> 3200 | H104: =SUM(H83:H103) -> 5180 | I104: =SUM(I83:I103) -> 1240 | J104: =SUM(J83:J103) -> 2620 | ... N104: =SUM(N83:N103) -> 1490 | P104: =SUM(P83:P103) -> 31510
...

Sheet Transfert
J3: =SUBTOTAL(9,J4:J81) -> 43200
E4: Date | F4: Année | G4: Mois | H4: Mode Paiement | I4: Banque | J4: Montant
E5: 44712 | F5: =YEAR(E5) -> 2022 | G5: =MONTH(E5) -> 5 | H5: Chèque | I5: BP | J5: 1680
E6: 44651 | F6: =YEAR(E6) -> 2022 | G6: =MONTH(E6) -> 3 | H6: Virement | I6: BP | J6: 840
E7: 44807 | F7: =YEAR(E7) -> 2022 | G7: =MONTH(E7) -> 9 | H7: Chèque | I7: TGR | J7: 1120
E8: 44601 | F8: =YEAR(E8) -> 2022 | G8: =MONTH(E8) -> 2 | H8: Chèque | I8: BP | J8: 1680
E9: 44789 | F9: =YEAR(E9) -> 2022 | G9: =MONTH(E9) -> 8 | H9: Chèque | I9: TGR | J9: 840
E10: 44807 | F10: =YEAR(E10) -> 2022 | G10: =MONTH(E10) -> 9 | H10: Chèque | I10: TGR | J10: 1120
E11: 44614 | F11: =YEAR(E11) -> 2022 | G11: =MONTH(E11) -> 2 | H11: Chèque | I11: BP | J11: 840
E12: 44747 | F12: =YEAR(E12) -> 2022 | G12: =MONTH(E12) -> 7 | H12: Chèque | I12: TGR | J12: 840
E13: 44909 | F13: =YEAR(E13) -> 2022 | G13: =MONTH(E13) -> 12 | H13: Chèque | I13: TGR | J13: 840
E14: 44614 | F14: =YEAR(E14) -> 2022 | G14: =MONTH(E14) -> 2 | H14: Chèque | I14: BP | J14: 50
E15: 44713 | F15: =YEAR(E15) -> 2022 | G15: =MONTH(E15) -> 6 | H15: Chèque | I15: BP | J15: 1680
E16: 44713 | F16: =YEAR(E16) -> 2022 | G16: =MONTH(E16) -> 6 | H16: Chèque | I16: BP | J16: 50
... E81: 44579 | F81: =YEAR(E81) -> 2022 | G81: =MONTH(E81) -> 1 | H81: Virement | I81: BP | J81: 100

Sheet 2023
F2: SITUATION DES COTISATIONS
M3: Immeuble | N3: 1
M4: Année | N4: 2023
A5: Apprt | B5: Copropriétaire | C5: Janvier | D5: Février | E5: Mars | F5: Avril | G5: Mai | H5: Juin | I5: Juillet | J5: Aout | K5: Septembre | L5: Octobre | M5: Novembre | N5: Décembre | O5: Garage | P5: Total | Q5: Remarques
A6: 1 | B6: LAHRACH YOUNES | C6: PAYE | D6: PAYE | E6: 260 | F6: PAYE | G6: 260 | H6: PAYE | J6: 260 | K6: PAYE | M6: 390 | P6: =SUM(C6:O6) -> 1170 | R6: 130
A7: 2 | B7: YABOURI MED | C7: 140 | D7: PAYE | E7: 280 | F7: PAYE | G7: 140 | H7: 140 | I7: 280 | J7: PAYE | K7: 280 | P7: =SUM(C7:O7) -> 1260 | R7: 140
A8: 3 | B8: EL BAKKALI IDRISSI | C8: PAYE | M8: 980 | P8: =SUM(C8:O8) -> 980 | R8: 140
A9: 4 | B9: BALBOUL LAHCEN | C9: 140 | D9: 140 | E9: 140 | F9: 140 | G9: 140 | H9: PAYE | I9: 140 | J9: 140 | K9: 280 | L9: 140 | M9: 140 | P9: =SUM(C9:O9) -> 1540 | R9: 140
A10: 5 | B10: IDRISSI MOKHTAR | C10: PAYE | D10: 140 | E10: PAYE | F10: 280 | G10: PAYE | H10: 420 | I10: PAYE | J10: PAYE | K10: 280 | L10: 280 | P10: =SUM(C10:O10) -> 1400 | R10: 140
A11: 6 | B11: HICHAM MANSOUR | C11: PAYE | K11: 1680 | L11: PAYE | P11: =SUM(C11:O11) -> 1680 | R11: 140
A12: 7 | B12: BENJELLOUN AMINE | C12: 260 | D12: PAYE | E12: 260 | F12: PAYE | G12: PAYE | H12: 260 | I12: PAYE | K12: 130 | L12: 260 | M12: 260 | P12: =SUM(C12:O12) -> 1430 | R12: 130
A13: 8 | B13: CHERKAOUI MOHAMED | C13: 140 | D13: 280 | E13: PAYE | F13: 140 | G13: 280 | H13: PAYE | I13: 280 | J13: 140 | K13: PAYE | M13: 280 | P13: =SUM(C13:O13) -> 1540 | R13: 140
A14: 9 | B14: HIMDI FAROUK | C14: 420 | D14: 280 | E14: 140 | F14: 140 | G14: PAYE | I14: 280 | J14: 280 | K14: PAYE | L14: 280 | P14: =SUM(C14:O14) -> 1820 | R14: 140
A15: 10 | B15: BENHAMMOU MOHAMED | C15: 140 | D15: 140 | E15: 280 | F15: 140 | G15: 140 | H15: PAYE | J15: 280 | K15: 140 | L15: 140 | M15: 140 | P15: =SUM(C15:O15) -> 1540 | R15: 140
A16: 11 | B16: BOUFOUS KHALID | C16: PAYE | M16: 1560 | P16: =SUM(C16:O16) -> 1560 | Q16: janvier à novembre 2023 payé le 19/11/22 | R16: 140
A17: 12 | B17: EL OUARCHITI MOHAMED | C17: PAYE | F17: 840 | G17: PAYE | K17: 840 | L17: PAYE | P17: =SUM(C17:O17) -> 1680 | R17: 140
A18: 13 | B18: HéritiersBENKARACHE | C18: PAYE | D18: 280 | E18: PAYE | F18: 140 | G18: 280 | H18: PAYE | I18: 280 | J18: 140 | K18: 280 | L18: PAYE | O18: 150 | P18: =SUM(C18:O18) -> 1550 | R18: 140
A19: 14 | B19: Mme CHERKAOUI | C19: PAYE | H19: 2520 | P19: =SUM(C19:O19) -> 2520 | R19: 140
A20: 15 | B20: ALOUI LHOUCINE | C20: 130 | D20: 130 | E20: 130 | F20: 130 | G20: 130 | H20: 130 | I20: 260 | J20: PAYE | K20: 130 | L20: 260 | P20: =SUM(C20:O20) -> 1430 | R20: 130
A21: 16 | B21: Madame LATRACH | C21: 140 | D21: 140 | E21: PAYE | F21: 140 | G21: 280 | H21: PAYE | I21: 140 | J21: 280 | K21: 140 | L21: 140 | M21: 140 | P21: =SUM(C21:O21) -> 1540 | R21: 140
A22: 17 | B22: LAZRAK | C22: 1680 | D22: PAYE | P22: =SUM(C22:O22) -> 1680 | R22: 140
A23: 18 | B23: KEZZOULI ABDELGHANI | C23: PAYE | F23: 1680 | G23: PAYE | P23: =SUM(C23:O23) -> 1680 | R23: 140
A24: 19 | B24: YOUSFI SANAE | C24: PAYE | H24: 1300 | P24: =SUM(C24:O24) -> 1300 | R24: 130
A25: 20 | B25: CHBANI KACEM | C25: PAYE | G25: 700 | H25: PAYE | K25: 560 | P25: =SUM(C25:O25) -> 1260 | R25: 140
A26: Total | C26: =SUM(C6:C25) -> 3190 | D26: =SUM(D6:D25) -> 1530 | E26: =SUM(E6:E25) -> 1490 | F26: =SUM(F6:F25) -> 3770 | G26: =SUM(G6:G25) -> 2350 | H26: =SUM(H6:H25) -> 4770 | I26: =SUM(I6:I25) -> 1660 | J26: =SUM(J6:J25) -> 1520 | ... P26: =SUM(P6:P25) -> 30560
F28: SITUATION DES COTISATIONS
M29: Immeuble | N29: 2
M30: Année | N30: 2023
A31: Apprt | B31: Copropriétaire | C31: Janvier | D31: Février | E31: Mars | F31: Avril | G31: Mai | H31: Juin | I31: Juillet | J31: Aout | K31: Septembre | L31: Octobre | M31: Novembre | N31: Décembre | O31: Garage | P31: Total | Q31: Remarques
A32: 1 | B32: ASKAOUI | C32: 280 | D32: PAYE | E32: 280 | F32: PAYE | G32: 140 | H32: 140 | I32: 140 | J32: 140 | K32: PAYE | L32: 280 | O32: 100 | P32: =SUM(C32:O32) -> 1500
A33: 2 | B33: MELLOUKI | P33: =SUM(C33:O33) -> 0
A34: 3 | B34: BOURAS | P34: =SUM(C34:O34) -> 0
A35: 4 | B35: ABDESSADEK | C35: PAYE | D35: 420 | E35: 280 | F35: PAYE | H35: 280 | I35: PAYE | K35: 280 | M35: 280 | P35: =SUM(C35:O35) -> 1540
A36: 5 | B36: MME BOUAYAD | C36: 140 | D36: 280 | E36: PAYE | F36: 140 | G36: PAYE | H36: 280 | I36: PAYE | J36: 280 | K36: PAYE | L36: 280 | O36: 200 | P36: =SUM(C36:O36) -> 1600
A37: 6 | B37: TOK HASSAN | C37: PAYE | E37: 1680 | O37: 50 | P37: =SUM(C37:O37) -> 1730
A38: 7 | B38: BELFKIH MUSTAFA | C38: PAYE | G38: 560 | H38: 140 | I38: PAYE | J38: 420 | K38: PAYE | L38: 280 | O38: 150 | P38: =SUM(C38:O38) -> 1550
A39: 8 | B39: OUHNAOUI MOHAMED | C39: 1680 | D39: PAYE | I39: 1680 | J39: PAYE | P39: =SUM(C39:O39) -> 3360
A40: 9 | B40: BOURI | C40: PAYE | K40: 1820 | P40: =SUM(C40:O40) -> 1820
A41: 10 | B41: Héritiers MERNISSI | C41: PAYE | E41: 560 | F41: PAYE | G41: PAYE | H41: 700 | I41: PAYE | K41: 840 | L41: PAYE | P41: =SUM(C41:O41) -> 2100
A42: 11 | B42: DIOURI ABBES | C42: PAYE | I42: 840 | J42: PAYE | O42: 50 | P42: =SUM(C42:O42) -> 890
A43: 12 | B43: MAADAD ABDELKADER | C43: PAYE | H43: 1680 | I43: PAYE | O43: 50 | P43: =SUM(C43:O43) -> 1730
A44: 13 | B44: ETTAZI | C44: 900 | D44: PAYE | I44: PAYE | M44: 900 | N44: PAYE | O44: 250 | P44: =SUM(C44:O44) -> 2050
A45: 14 | B45: HADDOUCHI | C45: PAYE | F45: 840 | G45: PAYE | I45: PAYE | L45: 840 | M45: PAYE | O45: 50 | P45: =SUM(C45:O45) -> 1730
A46: 15 | B46: EL KMITI | C46: 140 | D46: 280 | E46: PAYE | F46: 140 | G46: 280 | H46: PAYE | I46: 280 | J46: 140 | K46: PAYE | M46: 280 | O46: 250 | P46: =SUM(C46:O46) -> 1790
A47: 16 | B47: BENABDESLAM AHMED | C47: 900 | D47: PAYE | I47: 900 | J47: PAYE | O47: 50 | P47: =SUM(C47:O47) -> 1850
A48: 17 | B48: LAASOULI (HERITIERS) | C48: PAYE | D48: PAYE | H48: 750 | I48: PAYE | M48: 900 | N48: PAYE | P48: =SUM(C48:O48) -> 1650
A49: Total | C49: =SUM(C29:C48) -> 4040 | D49: =SUM(D29:D48) -> 980 | E49: =SUM(E29:E48) -> 2800 | F49: =SUM(F29:F48) -> 1120 | G49: =SUM(G29:G48) -> 980 | H49: =SUM(H29:H48) -> 3970 | I49: =SUM(I29:I48) -> 3840 | J49: =SUM(J29:J48) -> 980 | ... N49: =SUM(N29:N48) -> 2025 | P49: =SUM(P32:P48) -> 26890
F52: SITUATION DES COTISATIONS
M53: Immeuble | N53: 3
M54: Année | N54: 2023
A55: Apprt | B55: Copropriétaire | C55: Janvier | D55: Février | E55: Mars | F55: Avril | G55: Mai | H55: Juin | I55: Juillet | J55: Aout | K55: Septembre | L55: Octobre | M55: Novembre | N55: Décembre | O55: Garage | P55: Total | Q55: Remarques
A56: 1 | B56: BERKA (HERITIERS) | C56: 390 | D56: PAYE | G56: 390 | H56: PAYE | J56: 390 | P56: =SUM(C56:O56) -> 1170
A57: 2 | B57: HAMMOUTAHAR AHMED | C57: 280 | D57: 280 | E57: 280 | F57: 280 | G57: 280 | H57: PAYE | I57: 280 | J57: PAYE | P57: =SUM(C57:O57) -> 1680
A58: 3 | B58: ALAOUI ALI | C58: 390 | D58: 260 | E58: PAYE | H58: 520 | I58: PAYE | K58: 260 | L58: PAYE | M58: 390 | P58: =SUM(C58:O58) -> 1820
A59: 5 | B59: Mme AGNAOU Malika | C59: PAYE | K59: 1560 | P59: =SUM(C59:O59) -> 1560
A60: 6 | B60: OUCHRAE | C60: PAYE | D60: 1300 | E60: PAYE | J60: 780 | P60: =SUM(C60:O60) -> 2080
A61: 7 | B61: AOURARH LHOUCINE | C61: 130 | D61: 130 | E61: 260 | F61: 130 | G61: 130 | H61: 130 | I61: 130 | J61: 130 | K61: 130 | L61: 130 | P61: =SUM(C61:O61) -> 1430
A62: 8 | B62: BENJELLOUN | C62: 280 | D62: PAYE | E62: 280 | F62: 140 | G62: 140 | H62: PAYE | I62: 280 | J62: 280 | K62: 280 | L62: PAYE | M62: 140 | N62: PAYE | P62: =SUM(C62:O62) -> 1820
A63: 9 | B63: HAYARI MOHAMED | C63: PAYE | D63: 520 | E63: PAYE | G63: 390 | H63: PAYE | I63: 260 | J63: PAYE | L63: 780 | M63: 1560 | N63: PAYE | P63: =SUM(C63:O63) -> 3510 | Q63: Année 2024 Payé le 27/11/2023
A64: 10 | B64: GHISSASSI | C64: PAYE | D64: 1560 | E64: PAYE | P64: =SUM(C64:O64) -> 1560
A65: 11 | B65: IBRAHIMI | P65: =SUM(C65:O65) -> 0
A66: 12 | B66: ALAOUI | P66: =SUM(C66:O66) -> 0
A67: 13 | B67: KABILA | C67: PAYE | D67: 260 | E67: PAYE | G67: 260 | H67: PAYE | I67: 260 | J67: PAYE | K67: 260 | L67: PAYE | M67: 260 | P67: =SUM(C67:O67) -> 1300
A68: 14 | B68: MOUSSAOUI | C68: PAYE | P68: =SUM(C68:O68) -> 0 | Q68: Paiement efféctué le 23/08/2022
A69: 15 | B69: YASSINE | C69: PAYE | G69: 1560 | H69: PAYE | P69: =SUM(C69:O69) -> 1560
A70: 16 | B70: BOUSFIHA (HERITIERS) | C70: PAYE | I70: 840 | P70: =SUM(C70:O70) -> 840
A71: 17 | B71: SANJARI | C71: PAYE | H71: 780 | I71: 780 | J71: PAYE | P71: =SUM(C71:O71) -> 1560
A72: 18 | B72: BERICHE FATIMA | C72: PAYE | D72: 390 | E72: PAYE | F72: PAYE | G72: 260 | H72: 260 | I72: PAYE | J72: PAYE | L72: 390 | P72: =SUM(C72:O72) -> 1300
A73: 19 | B73: BENNIS ASSIA | C73: PAYE | I73: 1040 | P73: =SUM(C73:O73) -> 1040
A74: 20 | B74: EL YOUBI | P74: =SUM(C74:O74) -> 0
A75: Total | C75: =SUM(C55:C74) -> 1470 | D75: =SUM(D55:D74) -> 4700 | E75: =SUM(E55:E74) -> 820 | F75: =SUM(F55:F74) -> 550 | G75: =SUM(G55:G74) -> 3410 | H75: =SUM(H55:H74) -> 1690 | I75: =SUM(I55:I74) -> 3870 | J75: =SUM(J55:J74) -> 1580 | ... N75: =SUM(N55:N74) -> 0 | P75: =SUM(P56:P74) -> 24230
F77: SITUATION DES COTISATIONS
M78: Immeuble | N78: 4
M79: Année | N79: 2023
A80: Apprt | B80: Copropriétaire | C80: Janvier | D80: Février | E80: Mars | F80: Avril | G80: Mai | H80: Juin | I80: Juillet | J80: Aout | K80: Septembre | L80: Octobre | M80: Novembre | N80: Décembre | O80: Garage | P80: Total | Q80: Remarques
A81: 1 | B81: TIBRI/MANTEK | C81: PAYE | D81: 200 | E81: 300 | F81: PAYE | G81: 280 | P81: =SUM(C81:O81) -> 780
A82: 2 | B82: AANOUZ SAID | C82: PAYE | G82: 1680 | H82: PAYE | P82: =SUM(C82:O82) -> 1680
A83: 3 | B83: Mme ALAMI ABDELKADER | C83: PAYE | E83: 700 | F83: 140 | G83: 280 | H83: 140 | I83: 140 | J83: 140 | K83: 140 | L83: 140 | M83: 140 | P83: =SUM(C83:O83) -> 1960
A84: 4 | B84: EL GHOULI (HERITIERS) | C84: 420 | D84: PAYE | G84: 560 | H84: PAYE | I84: 280 | J84: PAYE | M84: 700 | O84: 250 | P84: =SUM(C84:O84) -> 2210
A85: 5 | B85: TAMIM AHMED | C85: PAYE | E85: 1680 | F85: PAYE | P85: =SUM(C85:O85) -> 1680
A86: 6 | B86: LAHMANI | D86: PAYE | F86: 420 | G86: PAYE | I86: 420 | J86: PAYE | L86: 420 | M86: PAYE | P86: =SUM(C86:O86) -> 1260 | Q86: chque KBC9001090 annule KBC9001086
A87: 7 | B87: BOUKRAA | C87: PAYE | E87: PAYE | H87: 640 | I87: 370 | J87: 160
B88: location garage syndic | C88: PAYE | H88: 1260 | I88: 630 | J88: 340 | P88: =SUM(C88:O88) -> 2230
A89: 8 | B89: EL ALAMI MOHAMED | C89: 140 | D89: 140 | E89: PAYE | F89: 280 | G89: PAYE | H89: 140 | I89: 140 | J89: 140 | K89: 140 | L89: PAYE | M89: 560 | N89: PAYE | P89: =SUM(C89:O89) -> 1680
A90: 9 | B90: LAHMIDI MOHAMED | C90: 140 | D90: 140 | E90: 140 | F90: 140 | G90: 280 | H90: PAYE | I90: 140 | J90: 140 | K90: 140 | L90: 140 | M90: 280 | P90: =SUM(C90:O90) -> 1680
A91: 10 | B91: RAMZI (HERITIERS) | P91: =SUM(C91:O91) -> 0
A92: 11 | B92: TIDAF MILOUD | C92: 130 | D92: PAYE | E92: 260 | F92: 130 | G92: 130 | H92: 130 | I92: 130 | J92: 130 | K92: 130 | L92: 130 | M92: 130 | P92: =SUM(C92:O92) -> 1430
A93: 12 | B93: NAHAL BACHIR | C93: 420 | D93: PAYE | E93: 420 | F93: PAYE | H93: PAYE | I93: 420 | J93: PAYE | K93: 420 | L93: PAYE | P93: =SUM(C93:O93) -> 1680
A94: 13 | B94: EL FREM TAHAR | C94: 1680 | D94: PAYE | P94: =SUM(C94:O94) -> 1680
A95: 14 | B95: Mme SEBBANE | C95: 140 | D95: PAYE | E95: 280 | F95: PAYE | G95: 280 | H95: PAYE | I95: 280 | J95: PAYE | K95: 280 | L95: 140 | P95: =SUM(C95:O95) -> 1400
A96: 15 | B96: NAFIE MOHAMED | C96: PAYE | D96: 260 | E96: PAYE | F96: 260 | P96: =SUM(C96:O96) -> 520
A97: 16 | B97: AIT DAHI MOHAMED | C97: 140 | D97: PAYE | E97: 280 | F97: PAYE | G97: 140 | H97: 280 | I97: PAYE | J97: 140 | K97: 140 | L97: 140 | M97: 140 | P97: =SUM(C97:O97) -> 1400
A98: 17 | B98: BOUOUD AHMED | C98: 420 | D98: PAYE | G98: 840 | K98: 420 | P98: =SUM(C98:O98) -> 1680 | Q98: Versé sur TGR
A99: 18 | B99: ATMANE MOHAMED | C99: PAYE | D99: 420 | E99: PAYE | F99: 420 | G99: PAYE | I99: 420 | J99: PAYE | L99: 420 | M99: PAYE | P99: =SUM(C99:O99) -> 1680
A100: 19 | B100: EL FILALI KHADIJA | C100: PAYE | D100: 130 | E100: 260 | F100: PAYE | G100: 260 | H100: 130 | I100: 130 | J100: 130 | K100: 130 | L100: 130 | M100: 130 | P100: =SUM(C100:O100) -> 1430
A101: 20 | B101: OUDGHIRI NOUZHA | C101: 840 | D101: PAYE | E101: 840 | F101: PAYE | P101: =SUM(C101:O101) -> 1680
A102: Total | C102: =SUM(C82:C101) -> 4470 | D102: =SUM(D82:D101) -> 1090 | E102: =SUM(E82:E101) -> 4860 | F102: =SUM(F82:F101) -> 1790 | G102: =SUM(G82:G101) -> 4450 | H102: =SUM(H82:H101) -> 2720 | I102: =SUM(I82:I101) -> 3500 | J102: =SUM(J82:J101) -> 1320 | ... N102: =SUM(N82:N101) -> 0 | P102: =SUM(P83:P101) -> 27280
F104: SITUATION DES COTISATIONS
M105: Immeuble | N105: 5
M106: Année | N106: 2023
...

Sheet Recettes
M1: Année
L2: Total Chèque | M2: 2022 | N2: =SUMIFS(Tableau3[[#All],[Montant]],Tableau3[[#All],[Mode Recette]],"Espèce",Tableau3[[#All],[Année]],M2) -> 22837
L4: Total Espèce | M4: 2022 | N4: =SUMIFS(Tableau3[[#All],[Montant]],Tableau3[[#All],[Mode Recette]],"Chèque",Tableau3[[#All],[Année]],M4) -> 4000
J5: =SUBTOTAL(109,J6:J68) -> 9303 | N5: =SUMIFS(J6:J68,I6:I68,"2022",H6:H68,"1",D6:D68,"Espèce") -> 0 | P5: =SUMIFS(J6:J68,I6:I68,"2022",H6:H68,"1",D6:D68,"Espèce") -> 0
B6: Recette | C6: Type de Recette | D6: Mode Recette | E6: N° Pièce | F6: Banque | G6: Date | H6: Mois | I6: Année | J6: Montant | K6: Remarques
C7: Loyer Appart | D7: Virement | F7: BP | G7: 44566 | H7: =MONTH(G7) -> 1 | I7: =YEAR(Tableau3[[#This Row],[Date]]) -> 2022 | J7: 3500 | K7: janvier BP
C8: Loyer Appart | D8: Virement | F8: BP | G8: 44600 | H8: =MONTH(G8) -> 2 | I8: =YEAR(Tableau3[[#This Row],[Date]]) -> 2022 | J8: 3500 | K8: fevrier BP
C9: Loyer Appart | D9: Virement | F9: BP | G9: 44621 | H9: =MONTH(G9) -> 3 | I9: =YEAR(Tableau3[[#This Row],[Date]]) -> 2022 | J9: 3500 | K9: mars BP
C10: Loyer Appart | D10: Virement | F10: BP | G10: 44657 | H10: =MONTH(G10) -> 4 | I10: =YEAR(Tableau3[[#This Row],[Date]]) -> 2022 | J10: 3500 | K10: avril BP
C11: Loyer Appart | D11: Virement | F11: BP | G11: 44691 | H11: =MONTH(G11) -> 5 | I11: =YEAR(Tableau3[[#This Row],[Date]]) -> 2022 | J11: 3500 | K11: mai BP
C12: Loyer Appart | D12: Virement | F12: BP | G12: 43988 | H12: =MONTH(G12) -> 6 | I12: =YEAR(Tableau3[[#This Row],[Date]]) -> 2020 | J12: 3500 | K12: juin BP
C13: Loyer Appart | D13: Virement | F13: BP | G13: 44749 | H13: =MONTH(G13) -> 7 | I13: =YEAR(Tableau3[[#This Row],[Date]]) -> 2022 | J13: 3500 | K13: juillet BP
C14: Loyer Appart | D14: Virement | F14: BP | G14: 44781 | H14: =MONTH(G14) -> 8 | I14: =YEAR(Tableau3[[#This Row],[Date]]) -> 2022 | J14: 3500 | K14: aout BP
C15: Loyer Appart | D15: Virement | F15: BP | G15: 44810 | H15: =MONTH(G15) -> 9 | I15: =YEAR(Tableau3[[#This Row],[Date]]) -> 2022 | J15: 3500 | K15: septembre BP
C16: Loyer Appart | D16: Virement | F16: BP | G16: 44840 | H16: =MONTH(G16) -> 10 | I16: =YEAR(Tableau3[[#This Row],[Date]]) -> 2022 | J16: 3500 | K16: octobre BP
C17: Loyer Appart | D17: Virement | F17: BP | G17: 44873 | H17: =MONTH(G17) -> 11 | I17: =YEAR(Tableau3[[#This Row],[Date]]) -> 2022 | J17: 3500 | K17: novembre BP
C18: Loyer Appart | D18: Virement | F18: BP | G18: 44902 | H18: =MONTH(G18) -> 12 | I18: =YEAR(Tableau3[[#This Row],[Date]]) -> 2022 | J18: 3500 | K18: décembre BP
... C20: Loyer Appart | D20: Virement | F20: BP | G20: 44960 | H20: =MONTH(G20) -> 2 | I20: =YEAR(Tableau3[[#This Row],[Date]]) -> 2023 | J20: 3500 | K20: fevrier BP
C21: Loyer Economat | D21: Espèce | E21: 68/01 | G21: 44638 | H21: =MONTH(G21) -> 3 | I21: =YEAR(Tableau3[[#This Row],[Date]]) -> 2022 | J21: 1870 | K21: janvier 2022
C22: Loyer Economat | D22: Espèce | E22: 69/02 | G22: 44682 | H22: =MONTH(G22) -> 5 | I22: =YEAR(Tableau3[[#This Row],[Date]]) -> 2022 | J22: 1870 | K22: fevrier 2022
C23: Loyer Economat | D23: Espèce | E23: 70/03 | G23: 44710 | H23: =MONTH(G23) -> 5 | I23: =YEAR(Tableau3[[#This Row],[Date]]) -> 2022 | J23: 1870 | K23: mars 2022
C24: Loyer Economat | D24: Espèce | E24: 71/04 | G24: 44745 | H24: =MONTH(G24) -> 7 | I24: =YEAR(Tableau3[[#This Row],[Date]]) -> 2022 | J24: 1870 | K24: avril 2022
C25: Loyer Economat | D25: Espèce | E25: 72/05 | G25: 44780 | H25: =MONTH(G25) -> 8 | I25: =YEAR(Tableau3[[#This Row],[Date]]) -> 2022 | J25: 1870 | K25: mai 2022
C26: Loyer Economat | D26: Espèce | E26: 73/06 | G26: 44803 | H26: =MONTH(G26) -> 8 | I26: =YEAR(Tableau3[[#This Row],[Date]]) -> 2022 | J26: 1870 | K26: juin 2022
C27: Loyer Economat | D27: Espèce | E27: 74/07 | G27: 44822 | H27: =MONTH(G27) -> 9 | I27: =YEAR(Tableau3[[#This Row],[Date]]) -> 2022 | J27: 1870 | K27: juillet
C28: Loyer Economat | D28: Chèque | E28: 75/08 | F28: TGR | G28: 44850 | H28: =MONTH(G28) -> 10 | I28: =YEAR(Tableau3[[#This Row],[Date]]) -> 2022 | J28: 2000 | K28: aout (loyer: 1870,00; elect:130,00
C29: Loyer Economat | D29: Chèque | E29: 76/09 | F29: TGR | G29: 44881 | H29: =MONTH(G29) -> 11 | I29: =YEAR(Tableau3[[#This Row],[Date]]) -> 2022 | J29: 2000 | K29: septembre
C30: Loyer Economat | D30: Espèce | E30: 76/09 | G30: 44881 | H30: =MONTH(G30) -> 11 | I30: =YEAR(Tableau3[[#This Row],[Date]]) -> 2022 | J30: 50 | K30: septembre
C31: Loyer Economat | D31: Espèce | E31: 77/10 | G31: 44914 | H31: =MONTH(G31) -> 12 | I31: =YEAR(Tableau3[[#This Row],[Date]]) -> 2022 | J31: 2050 | K31: octobre
C32: Loyer Economat | D32: Espèce | E32: 78/11 | G32: 44946 | H32: =MONTH(G32) -> 1 | I32: =YEAR(Tableau3[[#This Row],[Date]]) -> 2023 | J32: 2050 | K32: novembre
C33: Loyer Economat | D33: Espèce | E33: 79/12 | G33: 44984 | H33: =MONTH(G33) -> 2 | I33: =YEAR(Tableau3[[#This Row],[Date]]) -> 2023 | J33: 2050 | K33: decembre
C34: Electricité Economat | D34: Espèce | G34: 44803 | H34: =MONTH(G34) -> 8 | I34: =YEAR(Tableau3[[#This Row],[Date]]) -> 2022 | J34: 189 | K34: mai 20020
C35: Electricité Economat | D35: Espèce | G35: 44822 | H35: =MONTH(G35) -> 9 | I35: =YEAR(Tableau3[[#This Row],[Date]]) -> 2022 | J35: 484 | K35: juillet & aout 2020
C36: Electricité Economat | D36: Espèce | G36: 44850 | H36: =MONTH(G36) -> 10 | I36: =YEAR(Tableau3[[#This Row],[Date]]) -> 2022 | J36: 452 | K36: septembre & octobre 2020
C37: Electricité Economat | D37: Espèce | G37: 44881 | H37: =MONTH(G37) -> 11 | I37: =YEAR(Tableau3[[#This Row],[Date]]) -> 2022 | J37: 318 | K37: novembre & decembre 2020
C38: Electricité Economat | D38: Espèce | G38: 44914 | H38: =MONTH(G38) -> 12 | I38: =YEAR(Tableau3[[#This Row],[Date]]) -> 2022 | J38: 224 | K38: janvier & fevrier 2021
C39: Electricité Economat | D39: Espèce | G39: 44946 | H39: =MONTH(G39) -> 1 | I39: =YEAR(Tableau3[[#This Row],[Date]]) -> 2023 | J39: 253 | K39: mars & avril 2021
C40: Electricité Economat | D40: Espèce | G40: 44984 | H40: =MONTH(G40) -> 2 | I40: =YEAR(Tableau3[[#This Row],[Date]]) -> 2023 | J40: 698 | K40: mai & juin 2021
C41: Loyer Garage | D41: Espèce | G41: 44610 | H41: =MONTH(G41) -> 2 | I41: =YEAR(Tableau3[[#This Row],[Date]]) -> 2022 | J41: 2830 | K41: mars à novembre 2021
C42: Loyer Garage | D42: Espèce | G42: 44826 | H42: =MONTH(G42) -> 9 | I42: =YEAR(Tableau3[[#This Row],[Date]]) -> 2022 | J42: 3150 | K42: decembre 2021 à septembre2022
C43: Loyer Economat | D43: Espèce | E43: 80/01 | G43: 45008 | H43: =MONTH(G43) -> 3 | I43: =YEAR(Tableau3[[#This Row],[Date]]) -> 2023 | J43: 2050 | K43: 44927
C44: Electricité Economat | D44: Espèce | G44: 45008 | H44: =MONTH(G44) -> 3 | I44: =YEAR(Tableau3[[#This Row],[Date]]) -> 2023 | J44: 3775 | K44: juillet 2021 à juillet 2022
C45: Loyer Appart | D45: Virement | F45: BP | G45: 45015 | H45: =MONTH(G45) -> 3 | I45: =YEAR(Tableau3[[#This Row],[Date]]) -> 2023 | J45: 3500 | K45: mars BP
C46: Loyer Economat | D46: Espèce | E46: 81/02 | G46: 45020 | H46: =MONTH(G46) -> 4 | I46: =YEAR(Tableau3[[#This Row],[Date]]) -> 2023 | J46: 2050 | K46: fevrier
C47: Loyer Economat | D47: Espèce | E47: 82/03 | G47: 45026 | H47: =MONTH(G47) -> 4 | I47: =YEAR(Tableau3[[#This Row],[Date]]) -> 2023 | J47: 2050 | K47: mars
C48: Electricité Economat | D48: Espèce | G48: 45026 | H48: =MONTH(G48) -> 4 | I48: =YEAR(Tableau3[[#This Row],[Date]]) -> 2023 | J48: 992 | K48: Aout & septembre 2022
C49: Loyer Appart | D49: Virement | F49: BP | G49: 45028 | H49: =MONTH(G49) -> 4 | I49: =YEAR(Tableau3[[#This Row],[Date]]) -> 2023 | J49: 3500 | K49: avril BP
C50: Loyer Economat | D50: Espèce | E50: 83/04 | G50: 45059 | H50: =MONTH(G50) -> 5 | I50: =YEAR(Tableau3[[#This Row],[Date]]) -> 2023 | J50: 2050 | K50: avril
C51: Electricité Economat | D51: Espèce | G51: 45059 | H51: =MONTH(G51) -> 5 | I51: =YEAR(Tableau3[[#This Row],[Date]]) -> 2023 | J51: 720 | K51: octobre b& novembre 2022
C52: Loyer Appart | D52: Virement | F52: BP | G52: 45063 | H52: =MONTH(G52) -> 5 | I52: =YEAR(Tableau3[[#This Row],[Date]]) -> 2023 | J52: 3500 | K52: mai BP
C53: Loyer Economat | D53: Espèce | E53: 84/05 | G53: 45087 | H53: =MONTH(G53) -> 6 | I53: =YEAR(Tableau3[[#This Row],[Date]]) -> 2023 | J53: 2050 | K53: mai
C54: Electricité Economat | D54: Espèce | G54: 45087 | H54: =MONTH(G54) -> 6 | I54: =YEAR(Tableau3[[#This Row],[Date]]) -> 2023 | J54: 576 | K54: décembre 2022 & janvier 2023
C55: Loyer Appart | D55: Virement | F55: BP | G55: 45090 | H55: =MONTH(G55) -> 6 | I55: =YEAR(Tableau3[[#This Row],[Date]]) -> 2023 | J55: 3500 | K55: juin BP
C56: Loyer Appart | D56: Virement | F56: BP | G56: 45112 | H56: =MONTH(G56) -> 7 | I56: =YEAR(Tableau3[[#This Row],[Date]]) -> 2023 | J56: 3500 | K56: juillet BP
C57: Loyer Economat | D57: Espèce | E57: 85/06 | G57: 45127 | H57: =MONTH(G57) -> 7 | I57: =YEAR(Tableau3[[#This Row],[Date]]) -> 2023 | J57: 2050 | K57: juin
C58: Electricité Economat | D58: Espèce | G58: 45127 | H58: =MONTH(G58) -> 7 | I58: =YEAR(Tableau3[[#This Row],[Date]]) -> 2023 | J58: 583 | K58: février & mars 2023
C59: Loyer Appart | D59: Virement | F59: BP | G59: 45142 | H59: =MONTH(G59) -> 8 | I59: =YEAR(Tableau3[[#This Row],[Date]]) -> 2023 | J59: 3500 | K59: Août BP
C60: Loyer Economat | D60: Espèce | E60: 86/07 | G60: 45150 | H60: =MONTH(G60) -> 8 | I60: =YEAR(Tableau3[[#This Row],[Date]]) -> 2023 | J60: 2050 | K60: juillet
C61: Electricité Economat | D61: Espèce | G61: 45150 | H61: =MONTH(G61) -> 8 | I61: =YEAR(Tableau3[[#This Row],[Date]]) -> 2023 | J61: 623 | K61: avril & mai 2023
C62: Loyer Appart | D62: Virement | F62: BP | G62: 45174 | H62: =MONTH(G62) -> 9 | I62: =YEAR(Tableau3[[#This Row],[Date]]) -> 2023 | J62: 3500 | K62: septembre BP
C63: Loyer Economat | D63: Espèce | E63: 87/08 | G63: 45185 | H63: =MONTH(G63) -> 9 | I63: =YEAR(Tableau3[[#This Row],[Date]]) -> 2023 | J63: 2050 | K63: Aout
C64: Electricité Economat | D64: Espèce | G64: 45185 | H64: =MONTH(G64) -> 9 | I64: =YEAR(Tableau3[[#This Row],[Date]]) -> 2023 | J64: 813 | K64: juin & juillet 2023
C65: Loyer Appart | D65: Virement | F65: BP | G65: 45209 | H65: =MONTH(G65) -> 10 | I65: =YEAR(Tableau3[[#This Row],[Date]]) -> 2023 | J65: 3500 | K65: octobre BP
C66: Loyer Economat | D66: Espèce | E66: 88/09 | G66: 45215 | H66: =MONTH(G66) -> 10 | I66: =YEAR(Tableau3[[#This Row],[Date]]) -> 2023 | J66: 2050 | K66: septembre
C67: Electricité Economat | D67: Espèce | G67: 45215 | H67: =MONTH(G67) -> 10 | I67: =YEAR(Tableau3[[#This Row],[Date]]) -> 2023 | J67: 585 | K67: Aout
C68: Loyer Appart | D68: Virement | F68: BP | G68: 45241 | H68: =MONTH(G68) -> 11 | I68: =YEAR(Tableau3[[#This Row],[Date]]) -> 2023 | J68: 3500 | K68: novembre BP

Sheet Dépenses
N1: Année
M2: Total Chèque | N2: 2022 | O2: =SUMIFS(Tableau36[[#All],[Montant]],Tableau36[[#All],[Mode Paiement]],"Espèce",Tableau36[[#All],[Année]],N2) -> 132287
M4: Total Espèce | N4: 2023 | O4: =SUMIFS(Tableau36[[#All],[Montant]],Tableau36[[#All],[Mode Paiement]],"Chèque",Tableau36[[#All],[Année]],N4) -> 18856.15
K5: =SUBTOTAL(9,K6:K69) -> 0 | L5: Chèque | O5: =SUMIFS(Dépenses!$K$6:$K$336,C6:C336,"Divers") -> 23380.5
B6: Type de Pièce | C6: Catégorie | D6: Description Dépense | E6: Mode Paiement | F6: Banque | G6: N° Pièce | H6: Date | I6: Mois | J6: Année | K6: Montant | O6: =SUMIF(C6:C198,"Divers",K6:K198) -> 10497
B7: Dépenses Courantes | C7: Divers | D7: pourboir agents REDAL | E7: Espèce | H7: 44564 | I7: =MONTH(H7) -> 1 | J7: =YEAR(Tableau36[[#This Row],[Date]]) -> 2022 | K7: 100
B8: Téléphonie & Electricité | C8: Redal | D8: consommation du 12/21 | E8: Chèque | F8: BP | G8: bp:coc 6309625 | H8: 44564 | I8: =MONTH(H8) -> 1 | J8: =YEAR(Tableau36[[#This Row],[Date]]) -> 2022 | K8: 963.96
B9: Dépenses Courantes | C9: Entretien Electricité | D9: éclairage escalier Imm: 6 | E9: Espèce | H9: 44566 | I9: =MONTH(H9) -> 1 | J9: =YEAR(Tableau36[[#This Row],[Date]]) -> 2022 | K9: 150
B10: Dépenses Courantes | C10: Entretien Electricité | D10: pannel rond 12W Imm: 6 | E10: Espèce | H10: 44562 | I10: =MONTH(H10) -> 1 | J10: =YEAR(Tableau36[[#This Row],[Date]]) -> 2022 | K10: 105
B11: Dépenses Courantes | C11: Produits d'entretien | D11: eau de javel + nettoyant sol | E11: Espèce | H11: 44567 | I11: =MONTH(H11) -> 1 | J11: =YEAR(Tableau36[[#This Row],[Date]]) -> 2022 | K11: 70
B12: Téléphonie & Electricité | C12: Inwi | D12: forfait du 12/21 | E12: Prélèvement | F12: BP | H12: 44571 | I12: =MONTH(H12) -> 1 | J12: =YEAR(Tableau36[[#This Row],[Date]]) -> 2022 | K12: 199
B13: Dépenses Courantes | C13: Divers | D13: entretien PC | E13: Espèce | H13: 44573 | I13: =MONTH(H13) -> 1 | J13: 2022 | K13: 50
B14: Dépenses Courantes | C14: Divers | D14: frais médicaux Mbarek gardien | E14: Espèce | H14: 44573 | I14: =MONTH(H14) -> 1 | J14: =YEAR(Tableau36[[#This Row],[Date]]) -> 2022 | K14: 240
B15: Dépenses Courantes | C15: Produits d'entretien | D15: serpières | E15: Espèce | H15: 44581 | I15: =MONTH(H15) -> 1 | J15: =YEAR(Tableau36[[#This Row],[Date]]) -> 2022 | K15: 48
B16: Dépenses Courantes | C16: Divers | D16: débouchage regard Imm: 6 | E16: Espèce | H16: 44586 | I16: =MONTH(H16) -> 1 | J16: =YEAR(Tableau36[[#This Row],[Date]]) -> 2022 | K16: 500
B17: Travaux | C17: Travaux de Maçonnerie | D17: remise en état des acrotères | E17: Chèque | F17: BP | G17: bp:coc 6309626 | H17: 44591 | I17: =MONTH(H17) -> 1 | J17: =YEAR(Tableau36[[#This Row],[Date]]) -> 2022 | K17: 12384
B18: Paie & Primes & CNSS | C18: Prélèvement CNSS | D18: janvier | E18: Prélèvement | F18: BP | H18: 44603 | I18: =MONTH(H18) -> 2 | J18: =YEAR(Tableau36[[#This Row],[Date]]) -> 2022 | K18: 1885.72
B19: Paie & Primes & CNSS | C19: Paie Personnel | D19: janvier | E19: Espèce | H19: 44591 | I19: =MONTH(H19) -> 1 | J19: =YEAR(Tableau36[[#This Row],[Date]]) -> 2022 | K19: 8700
B20: Téléphonie & Electricité | C20: Redal | D20: consommation du 01/22 | E20: Chèque | F20: BP | G20: bp:AAA 1300001 | H20: 44593 | I20: =MONTH(H20) -> 2 | J20: =YEAR(Tableau36[[#This Row],[Date]]) -> 2022 | K20: 729.64
B21: Travaux | C21: Divers | D21: repose plaque: accès résérvé.. | E21: Espèce | H21: 44595 | I21: =MONTH(H21) -> 2 | J21: =YEAR(Tableau36[[#This Row],[Date]]) -> 2022 | K21: 70
B22: Téléphonie & Electricité | C22: Inwi | D22: forfait du 01/22 | E22: Prélèvement | F22: BP | H22: 44599 | I22: =MONTH(H22) -> 2 | J22: =YEAR(Tableau36[[#This Row],[Date]]) -> 2022 | K22: 199
B23: Dépenses Courantes | C23: Produits d'entretien | D23: détergent OMO | E23: Espèce | H23: 44608 | I23: =MONTH(H23) -> 2 | J23: =YEAR(Tableau36[[#This Row],[Date]]) -> 2022 | K23: 45
B24: Entretien Espaces Verts | C24: Essence - Huile | D24: essence | E24: Espèce | H24: 44613 | I24: =MONTH(H24) -> 2 | J24: =YEAR(Tableau36[[#This Row],[Date]]) -> 2022 | K24: 50
B25: Dépenses Courantes | C25: Divers | D25: débouchage regards RC Im: 6 | E25: Espèce | H25: 44615 | I25: =MONTH(H25) -> 2 | J25: =YEAR(Tableau36[[#This Row],[Date]]) -> 2022 | K25: 500
B26: Paie & Primes & CNSS | C26: Prélèvement CNSS | D26: fevrier | E26: Prélèvement | F26: BP | H26: 44631 | I26: =MONTH(H26) -> 3 | J26: =YEAR(Tableau36[[#This Row],[Date]]) -> 2022 | K26: 2514.3
B27: Paie & Primes & CNSS | C27: Paie Personnel | D27: fevrier | E27: Espèce | H27: 44620 | I27: =MONTH(H27) -> 2 | J27: =YEAR(Tableau36[[#This Row],[Date]]) -> 2022 | K27: 8700
B28: Paie & Primes & CNSS | C28: Paie Personnel | D28: Khadija remplacente Fatima | E28: Espèce | H28: 44614 | I28: =MONTH(H28) -> 2 | J28: =YEAR(Tableau36[[#This Row],[Date]]) -> 2022 | K28: 920
B29: Dépenses Courantes | C29: Produits d'entretien | E29: Espèce | H29: 44622 | I29: =MONTH(H29) -> 3 | J29: =YEAR(Tableau36[[#This Row],[Date]]) -> 2022 | K29: 72
B30: Téléphonie & Electricité | C30: Redal | D30: consommation du 02/22 | E30: Chèque | F30: BP | G30: bp:AAA 1300002 | H30: 44623 | I30: =MONTH(H30) -> 3 | J30: =YEAR(Tableau36[[#This Row],[Date]]) -> 2022 | K30: 831.18
B31: Dépenses Courantes | C31: Entretien Electricité | D31: ampoules B22 | E31: Espèce | H31: 44630 | I31: =MONTH(H31) -> 3 | J31: =YEAR(Tableau36[[#This Row],[Date]]) -> 2022 | K31: 60
B32: Téléphonie & Electricité | C32: Inwi | D32: forfait du 02/22 | E32: Prélèvement | F32: BP | H32: 44634 | I32: =MONTH(H32) -> 3 | J32: =YEAR(Tableau36[[#This Row],[Date]]) -> 2022 | K32: 199
B33: Travaux | C33: Travaux de Maçonnerie | D33: étanchéité acrotaires + divers | E33: Chèque | F33: BP | G33: bp:AAA 1300003 | H33: 44637 | I33: =MONTH(H33) -> 3 | J33: =YEAR(Tableau36[[#This Row],[Date]]) -> 2022 | K33: 20420
B34: Dépenses Courantes | C34: Produits d'entretien | E34: Espèce | H34: 44637 | I34: =MONTH(H34) -> 3 | J34: =YEAR(Tableau36[[#This Row],[Date]]) -> 2022 | K34: 190
B35: Dépenses Courantes | C35: Divers | D35: Béquille double porte local VO | E35: Espèce | H35: 44650 | I35: =MONTH(H35) -> 3 | J35: =YEAR(Tableau36[[#This Row],[Date]]) -> 2022 | K35: 70
B36: Dépenses Courantes | C36: Divers | D36: entretien réseau d'égout Im. 4 | E36: Espèce | H36: 44650 | I36: =MONTH(H36) -> 3 | J36: =YEAR(Tableau36[[#This Row],[Date]]) -> 2022 | K36: 300
B37: Entretien Espaces Verts | C37: Essence - Huile | D37: huile pour tondeuse à gazon | E37: Espèce | H37: 44650 | I37: =MONTH(H37) -> 3 | J37: =YEAR(Tableau36[[#This Row],[Date]]) -> 2022 | K37: 44
B38: Paie & Primes & CNSS | C38: Paie Personnel | D38: mars | E38: Espèce | H38: 44650 | I38: =MONTH(H38) -> 3 | J38: =YEAR(Tableau36[[#This Row],[Date]]) -> 2022 | K38: 8700
B39: Paie & Primes & CNSS | C39: Prélèvement CNSS | D39: mars | E39: Prélèvement | F39: BP | H39: 44662 | I39: =MONTH(H39) -> 4 | J39: =YEAR(Tableau36[[#This Row],[Date]]) -> 2022 | K39: 2514.3
B40: Téléphonie & Electricité | C40: Redal | D40: consommation du 03/22 | E40: Chèque | F40: BP | G40: bp:AAA 1300004 | H40: 44652 | I40: =MONTH(H40) -> 4 | J40: =YEAR(Tableau36[[#This Row],[Date]]) -> 2022 | K40: 865.07
B41: Dépenses Courantes | C41: Divers | D41: cartouche d'encre imprimante | E41: Espèce | H41: 44655 | I41: =MONTH(H41) -> 4 | J41: =YEAR(Tableau36[[#This Row],[Date]]) -> 2022 | K41: 160
B42: Téléphonie & Electricité | C42: Inwi | D42: forfait du 03/22 | E42: Prélèvement | F42: BP | H42: 44656 | I42: =MONTH(H42) -> 4 | J42: =YEAR(Tableau36[[#This Row],[Date]]) -> 2022 | K42: 199
B43: Dépenses Courantes | C43: Produits d'entretien | D43: savonettes | E43: Espèce | H43: 44663 | I43: =MONTH(H43) -> 4 | J43: =YEAR(Tableau36[[#This Row],[Date]]) -> 2022 | K43: 25
B44: Dépenses Courantes | C44: Entretien Electricité | D44: pannel rond led 12W Imm: 1 | E44: Espèce | H44: 44663 | I44: =MONTH(H44) -> 4 | J44: =YEAR(Tableau36[[#This Row],[Date]]) -> 2022 | K44: 168
B45: Entretien Espaces Verts | C45: Materiel/ pièces rechange | D45: fil coupe broussailles | E45: Espèce | H45: 44664 | I45: =MONTH(H45) -> 4 | J45: =YEAR(Tableau36[[#This Row],[Date]]) -> 2022 | K45: 50
B46: Dépenses Courantes | C46: Plomberie | D46: fuite conduite eaux usées Im:1 | E46: Espèce | H46: 44667 | I46: =MONTH(H46) -> 4 | J46: =YEAR(Tableau36[[#This Row],[Date]]) -> 2022 | K46: 400
B47: Entretien Espaces Verts | C47: installation de pompage | D47: tableau de commande | E47: Espèce | H47: 44667 | I47: =MONTH(H47) -> 4 | J47: =YEAR(Tableau36[[#This Row],[Date]]) -> 2022 | K47: 1000
B48: Entretien Espaces Verts | C48: Essence - Huile | D48: essence | E48: Espèce | H48: 44669 | I48: =MONTH(H48) -> 4 | J48: =YEAR(Tableau36[[#This Row],[Date]]) -> 2022 | K48: 40
B49: Dépenses Courantes | C49: Produits d'entretien | D49: insecticide | E49: Espèce | H49: 44672 | I49: =MONTH(H49) -> 4 | J49: =YEAR(Tableau36[[#This Row],[Date]]) -> 2022 | K49: 40
B50: Dépenses Courantes | C50: Plomberie | D50: conduite eau potable Im:2 apt3 | E50: Espèce | H50: 44672 | I50: =MONTH(H50) -> 4 | J50: =YEAR(Tableau36[[#This Row],[Date]]) -> 2022 | K50: 1000
B51: Dépenses Courantes | C51: Produits d'entretien | D51: eau de javel + nettoyant sol | E51: Espèce | H51: 44662 | I51: =MONTH(H51) -> 4 | J51: =YEAR(Tableau36[[#This Row],[Date]]) -> 2022 | K51: 71
B52: Paie & Primes & CNSS | C52: Paie Personnel | D52: avril | E52: Espèce | H52: 44681 | I52: =MONTH(H52) -> 4 | J52: =YEAR(Tableau36[[#This Row],[Date]]) -> 2022 | K52: 8700
B53: Paie & Primes & CNSS | C53: Primes Annuelles - Aid El Fitr | E53: Espèce | H53: 44681 | I53: =MONTH(H53) -> 4 | J53: =YEAR(Tableau36[[#This Row],[Date]]) -> 2022 | K53: 1200
B54: Paie & Primes & CNSS | C54: Prélèvement CNSS | D54: avril | E54: Prélèvement | F54: BP | H54: 44692 | I54: =MONTH(H54) -> 5 | J54: =YEAR(Tableau36[[#This Row],[Date]]) -> 2022 | K54: 2514.3
B55: Téléphonie & Electricité | C55: Redal | D55: consommation du 04/22 | E55: Chèque | F55: BP | G55: bp:AAA 1300005 | H55: 44686 | I55: =MONTH(H55) -> 5 | J55: =YEAR(Tableau36[[#This Row],[Date]]) -> 2022 | K55: 748.71
B56: Téléphonie & Electricité | C56: Inwi | D56: forfait du 04/22 | E56: Prélèvement | F56: BP | H56: 44688 | I56: =MONTH(H56) -> 5 | J56: =YEAR(Tableau36[[#This Row],[Date]]) -> 2022 | K56: 199
B57: Entretien Espaces Verts | C57: Essence - Huile | D57: essence | E57: Espèce | H57: 44691 | I57: =MONTH(H57) -> 5 | J57: =YEAR(Tableau36[[#This Row],[Date]]) -> 2022 | K57: 60
B58: Dépenses Courantes | C58: Divers | D58: réparation unité central PC | E58: Espèce | H58: 44695 | I58: =MONTH(H58) -> 5 | J58: =YEAR(Tableau36[[#This Row],[Date]]) -> 2022 | K58: 450
B59: Dépenses Courantes | C59: Divers | D59: colmatage gaine Im: 6; apt: 16 | E59: Espèce | H59: 44695 | I59: =MONTH(H59) -> 5 | J59: =YEAR(Tableau36[[#This Row],[Date]]) -> 2022 | K59: 200
B60: Dépenses Courantes | C60: Entretien Electricité | D60: lampes B22; Led STD 13W | E60: Espèce | H60: 44708 | I60: =MONTH(H60) -> 5 | J60: =YEAR(Tableau36[[#This Row],[Date]]) -> 2022 | K60: 216
B61: Dépenses Courantes | C61: Divers | D61: pourboir agents REDAL | E61: Espèce | H61: 44708 | I61: =MONTH(H61) -> 5 | J61: =YEAR(Tableau36[[#This Row],[Date]]) -> 2022 | K61: 150
B62: Entretien Espaces Verts | C62: Essence - Huile | D62: essence | E62: Espèce | H62: 44711 | I62: =MONTH(H62) -> 5 | J62: =YEAR(Tableau36[[#This Row],[Date]]) -> 2022 | K62: 75
B63: Dépenses Courantes | C63: Divers | D63: colliers de serrage | E63: Espèce | H63: 44711 | I63: =MONTH(H63) -> 5 | J63: =YEAR(Tableau36[[#This Row],[Date]]) -> 2022 | K63: 25
B64: Dépenses Courantes | C64: Plomberie | D64: conduite eau potable Im:5 apt12 | E64: Espèce | H64: 44712 | I64: =MONTH(H64) -> 5 | J64: =YEAR(Tableau36[[#This Row],[Date]]) -> 2022 | K64: 850
B65: Dépenses Courantes | C65: Produits d'entretien | D65: eau de javel + nettoyant sol | E65: Espèce | H65: 44712 | I65: =MONTH(H65) -> 5 | J65: =YEAR(Tableau36[[#This Row],[Date]]) -> 2022 | K65: 95
B66: Paie & Primes & CNSS | C66: Paie Personnel | D66: mai | E66: Espèce | H66: 44712 | I66: =MONTH(H66) -> 5 | J66: =YEAR(Tableau36[[#This Row],[Date]]) -> 2022 | K66: 8700
B67: Paie & Primes & CNSS | C67: Prélèvement CNSS | D67: mai | E67: Prélèvement | F67: BP | H67: 44723 | I67: =MONTH(H67) -> 6 | J67: =YEAR(Tableau36[[#This Row],[Date]]) -> 2022 | K67: 2514.3
B68: Dépenses Courantes | C68: Divers | D68: photocopies A3 | E68: Espèce | H68: 44562 | I68: =MONTH(H68) -> 1 | J68: =YEAR(Tableau36[[#This Row],[Date]]) -> 2022 | K68: 8.5
B69: Dépenses Courantes | C69: Divers | D69: scotch | E69: Espèce | H69: 44562 | I69: =MONTH(H69) -> 1 | J69: =YEAR(Tableau36[[#This Row],[Date]]) -> 2022 | K69: 3.5
B70: Téléphonie & Electricité | C70: Inwi | D70: forfait 05/22 | E70: Prélèvement | F70: BP | H70: 44718 | I70: =MONTH(H70) -> 6 | J70: =YEAR(Tableau36[[#This Row],[Date]]) -> 2022 | K70: 199
B71: Dépenses Courantes | C71: Entretien Electricité | D71: cage d'escalier Imm: 5 | E71: Espèce | H71: 44718 | I71: =MONTH(H71) -> 6 | J71: =YEAR(Tableau36[[#This Row],[Date]]) -> 2022 | K71: 100
B72: Entretien Espaces Verts | C72: Essence - Huile | D72: essence | E72: Espèce | H72: 44719 | I72: =MONTH(H72) -> 6 | J72: =YEAR(Tableau36[[#This Row],[Date]]) -> 2022 | K72: 90
B73: Téléphonie & Electricité | C73: Redal | D73: consommation du 05/22 | E73: Chèque | F73: BP | G73: bp:AAA 1300006 | H73: 44719 | I73: =MONTH(H73) -> 6 | J73: =YEAR(Tableau36[[#This Row],[Date]]) -> 2022 | K73: 1146.65
B74: Dépenses Courantes | C74: Produits d'entretien | D74: eau de javel + nettoyant sol | E74: Espèce | H74: 44720 | I74: =MONTH(H74) -> 6 | J74: =YEAR(Tableau36[[#This Row],[Date]]) -> 2022 | K74: 95
B75: Dépenses Courantes | C75: Plomberie | D75: conduite eau potable Im:6 apt16 | E75: Espèce | H75: 44725 | I75: =MONTH(H75) -> 6 | J75: =YEAR(Tableau36[[#This Row],[Date]]) -> 2022 | K75: 380
B76: Dépenses Courantes | C76: Divers | D76: pourboir agents Commune | E76: Espèce | H76: 44728 | I76: =MONTH(H76) -> 6 | J76: =YEAR(Tableau36[[#This Row],[Date]]) -> 2022 | K76: 100
B77: Paie & Primes & CNSS | C77: Paie Personnel | D77: 1ère quinzaine | E77: Espèce | H77: 44728 | I77: =MONTH(H77) -> 6 | J77: =YEAR(Tableau36[[#This Row],[Date]]) -> 2022 | K77: 4350
B78: Dépenses Courantes | C78: Divers | D78: photocopies AGO du 06/07/22 | E78: Espèce | H78: 44733 | I78: =MONTH(H78) -> 6 | J78: =YEAR(Tableau36[[#This Row],[Date]]) -> 2022 | K78: 80
B79: Dépenses Courantes | C79: Produits d'entretien | D79: eau de javel + nettoyant sol | E79: Espèce | H79: 44735 | I79: =MONTH(H79) -> 6 | J79: =YEAR(Tableau36[[#This Row],[Date]]) -> 2022 | K79: 95
B80: Dépenses Courantes | C80: Divers | D80: photocopies AGO du 06/07/22 | E80: Espèce | H80: 44736 | I80: =MONTH(H80) -> 6 | J80: =YEAR(Tableau36[[#This Row],[Date]]) -> 2022 | K80: 27
B81: Dépenses Courantes | C81: Divers | D81: gants pour femme de ménage | E81: Espèce | H81: 44738 | I81: =MONTH(H81) -> 6 | J81: =YEAR(Tableau36[[#This Row],[Date]]) -> 2022 | K81: 13
B82: Entretien Espaces Verts | C82: Essence - Huile | D82: essence | E82: Espèce | H82: 44741 | I82: =MONTH(H82) -> 6 | J82: =YEAR(Tableau36[[#This Row],[Date]]) -> 2022 | K82: 98
B83: Entretien Espaces Verts | C83: Essence - Huile | D83: hiule | E83: Espèce | H83: 44741 | I83: =MONTH(H83) -> 6 | J83: =YEAR(Tableau36[[#This Row],[Date]]) -> 2022 | K83: 145
B84: Paie & Primes & CNSS | C84: Paie Personnel | D84: 2ème quinzaine | E84: Espèce | H84: 44742 | I84: =MONTH(H84) -> 6 | J84: =YEAR(Tableau36[[#This Row],[Date]]) -> 2022 | K84: 4350
B85: Paie & Primes & CNSS | C85: Primes Annuelles - Aid Al Adha | E85: Espèce | H85: 44742 | I85: =MONTH(H85) -> 6 | J85: =YEAR(Tableau36[[#This Row],[Date]]) -> 2022 | K85: 3500
B86: Dépenses Courantes | C86: Divers | D86: réparation parabole TAMIM | E86: Espèce | H86: 44742 | I86: =MONTH(H86) -> 6 | J86: =YEAR(Tableau36[[#This Row],[Date]]) -> 2022 | K86: 100
B87: Paie & Primes & CNSS | C87: Prélèvement CNSS | D87: juin | E87: Prélèvement | F87: BP | H87: 44753 | I87: =MONTH(H87) -> 7 | J87: =YEAR(Tableau36[[#This Row],[Date]]) -> 2022 | K87: 2514.3
B88: Dépenses Courantes | C88: Divers | D88: cartouche pour imprimante | E88: Espèce | H88: 44743 | I88: =MONTH(H88) -> 7 | J88: =YEAR(Tableau36[[#This Row],[Date]]) -> 2022 | K88: 160
B89: Dépenses Courantes | C89: Divers | D89: colmatage gaine Im: 6; apt: 8 | E89: Espèce | H89: 44745 | I89: =MONTH(H89) -> 7 | J89: =YEAR(Tableau36[[#This Row],[Date]]) -> 2022 | K89: 200
B90: Dépenses Courantes | C90: Divers | D90: pourboir agents REDAL | E90: Espèce | H90: 44746 | I90: =MONTH(H90) -> 7 | J90: =YEAR(Tableau36[[#This Row],[Date]]) -> 2022 | K90: 100
B91: Téléphonie & Electricité | C91: Redal | D91: consommation du 06/22 | E91: Chèque | F91: BP | G91: bp:AAA 1300007 | H91: 44747 | I91: =MONTH(H91) -> 7 | J91: =YEAR(Tableau36[[#This Row],[Date]]) -> 2022 | K91: 1536.38
B92: Dépenses Courantes | C92: Divers | D92: serpière + manches balai | E92: Espèce | H92: 44748 | I92: =MONTH(H92) -> 7 | J92: =YEAR(Tableau36[[#This Row],[Date]]) -> 2022 | K92: 30
B93: Paie & Primes & CNSS | C93: Paie Personnel | D93: paiement R C M'barek | E93: Espèce | H93: 44748 | I93: =MONTH(H93) -> 7 | J93: =YEAR(Tableau36[[#This Row],[Date]]) -> 2022 | K93: 110
B94: Dépenses Courantes | C94: Divers | D94: sachets plastique | E94: Espèce | H94: 44749 | I94: =MONTH(H94) -> 7 | J94: =YEAR(Tableau36[[#This Row],[Date]]) -> 2022 | K94: 40
B95: Dépenses Courantes | C95: Produits d'entretien | D95: eau de javel + nettoyant sol | E95: Espèce | H95: 44751 | I95: =MONTH(H95) -> 7 | J95: =YEAR(Tableau36[[#This Row],[Date]]) -> 2022 | K95: 71
B96: Dépenses Courantes | C96: Divers | D96: sachets plastique/ poubelle | E96: Espèce | H96: 44751 | I96: =MONTH(H96) -> 7 | J96: =YEAR(Tableau36[[#This Row],[Date]]) -> 2022 | K96: 80
B97: Dépenses Courantes | C97: Divers | D97: photocopies AGO 2022 | E97: Espèce | H97: 44755 | I97: =MONTH(H97) -> 7 | J97: =YEAR(Tableau36[[#This Row],[Date]]) -> 2022 | K97: 24
B98: Paie & Primes & CNSS | C98: Paie Personnel | D98: 1ère quinzaine | E98: Espèce | H98: 44757 | I98: =MONTH(H98) -> 7 | J98: =YEAR(Tableau36[[#This Row],[Date]]) -> 2022 | K98: 4350
B99: Téléphonie & Electricité | C99: Inwi | D99: forfait 06/22 | E99: Prélèvement | F99: BP | H99: 44760 | I99: =MONTH(H99) -> 7 | J99: =YEAR(Tableau36[[#This Row],[Date]]) -> 2022 | K99: 199
B100: Dépenses Courantes | C100: Divers | D100: gants pour jardiniers | E100: Espèce | H100: 44762 | I100: =MONTH(H100) -> 7 | J100: =YEAR(Tableau36[[#This Row],[Date]]) -> 2022 | K100: 80
B101: Entretien Espaces Verts | C101: Essence - Huile | D101: essence | E101: Espèce | H101: 44764 | I101: =MONTH(H101) -> 7 | J101: =YEAR(Tableau36[[#This Row],[Date]]) -> 2022 | K101: 90
...

Sheet Récap 2022
B1: SITUATION 2022
F2: =SUMIFS(Transfert!J4:J81,Transfert!I4:I81,$E$5,Transfert!F4:F81,"2022",Transfert!G4:G81,A7) -> 6350
B3: RECETTES | H3: DEPENSES
C4: Caisse | E4: Banque | I4: Caisse | J4: Banque
B5: MOIS | C5: Cotisations | D5: Espèce | E5: BP | F5: TGR | G5: TOTAL | H5: MOIS | I5: Espèce | J5: BP | K5: TGR | L5: TOTAL
B6: REPORT: | G6: =+'[1]RECETTES 19 20 21'!Q75 -> 27235.72
A7: 1 | B7: Janv | C7: ='2022'!D158 - SUMIFS(Transfert!J4:J81,Transfert!F4:F81,"2022",Transfert!G4:G81,A7) -> 11730 | D7: =SUMIFS(Recettes!$J$6:$J$68,Recettes!$D$6:$D$68,$D$5,Recettes!$I$6:$I$68,"2022",Recettes!$H$6:$H$68,A7) -> 0 | E7: =SUMIFS(Recettes!$J$6:$J$68,Recettes!$F$6:$F$68,$E$5,Recettes!$I$6:$I$68,"2022",Recettes!$H$6:$H$68,A7) + SUMIFS(Transfert!J4:J81,Transfert!I4:I81,$E$5,Transfert!F4:F81,"2022",Transfert!G4:G81,A7) -> 9850 | F7: =SUMIFS(Recettes!$J$6:$J$68,Recettes!$F$6:$F$68,$F$5,Recettes!$I$6:$I$68,"2022",Recettes!$H$6:$H$68,A7) + SUMIFS(Transfert!K4:K81,Transfert!J4:J81,$F$5,Transfert!G4:G81,"2022",Transfert!H4:H81,A7) -> 0 | H7: Janv | I7: =SUMIFS(Dépenses!$K$6:$K$336,Dépenses!$E$6:$E$336,$I$5,Dépenses!$J$6:$J$336,"2022",Dépenses!$I$6:$I$336,A7) -> 9975 | J7: =SUMIFS(Dépenses!$K$6:$K$336,Dépenses!F6:F336,$J$5,Dépenses!$J$6:$J$336,"2022",Dépenses!$I$6:$I$336,A7) -> 13546.96 | K7: =SUMIFS(Dépenses!$K$6:$K$336,Dépenses!$F$6:$F$336,$K$5,Dépenses!$J$6:$J$336,"2022",Dépenses!$I$6:$I$336,A7) -> 0 | L7: =SUM(I7:K7) -> 23521.96
A8: 2 | B8: Fev | C8: ='2022'!D159 - SUMIFS(Transfert!J5:J81,Transfert!F5:F81,"2022",Transfert!G5:G81,A8) -> 12950 | D8: =SUMIFS(Recettes!$J$6:$J$68,Recettes!$D$6:$D$68,$D$5,Recettes!$I$6:$I$68,"2022",Recettes!$H$6:$H$68,A8) -> 2830 | E8: =SUMIFS(Recettes!$J$6:$J$68,Recettes!$F$6:$F$68,$E$5,Recettes!$I$6:$I$68,"2022",Recettes!$H$6:$H$68,A8) + SUMIFS(Transfert!J5:J81,Transfert!I5:I81,$E$5,Transfert!F5:F81,"2022",Transfert!G5:G81,A8) -> 11330 | F8: =SUMIFS(Recettes!$J$6:$J$68,Recettes!$F$6:$F$68,$F$5,Recettes!$I$6:$I$68,"2022",Recettes!$H$6:$H$68,A8) + SUMIFS(Transfert!K5:K81,Transfert!J5:J81,$F$5,Transfert!G5:G81,"2022",Transfert!H5:H81,A8) -> 0 | H8: Fev | I8: =SUMIFS(Dépenses!$K$6:$K$336,Dépenses!$E$6:$E$336,$I$5,Dépenses!$J$6:$J$336,"2022",Dépenses!$I$6:$I$336,A8) -> 10285 | J8: =SUMIFS(Dépenses!$K$6:$K$336,Dépenses!F7:F337,$J$5,Dépenses!$J$6:$J$336,"2022",Dépenses!$I$6:$I$336,A8) -> 570 | K8: =SUMIFS(Dépenses!$K$6:$K$336,Dépenses!$F$6:$F$336,$K$5,Dépenses!$J$6:$J$336,"2022",Dépenses!$I$6:$I$336,A8) -> 0 | L8: =SUM(I8:K8) -> 10855
A9: 3 | B9: Mars | C9: ='2022'!D160 - SUMIFS(Transfert!J6:J81,Transfert!F6:F81,"2022",Transfert!G6:G81,A9) -> 17100 | D9: =SUMIFS(Recettes!$J$6:$J$68,Recettes!$D$6:$D$68,$D$5,Recettes!$I$6:$I$68,"2022",Recettes!$H$6:$H$68,A9) -> 1870 | E9: =SUMIFS(Recettes!$J$6:$J$68,Recettes!$F$6:$F$68,$E$5,Recettes!$I$6:$I$68,"2022",Recettes!$H$6:$H$68,A9) + SUMIFS(Transfert!J6:J81,Transfert!I6:I81,$E$5,Transfert!F6:F81,"2022",Transfert!G6:G81,A9) -> 6380 | F9: =SUMIFS(Recettes!$J$6:$J$68,Recettes!$F$6:$F$68,$F$5,Recettes!$I$6:$I$68,"2022",Recettes!$H$6:$H$68,A9) + SUMIFS(Transfert!K6:K81,Transfert!J6:J81,$F$5,Transfert!G6:G81,"2022",Transfert!H6:H81,A9) -> 0 | H9: Mars | I9: =SUMIFS(Dépenses!$K$6:$K$336,Dépenses!$E$6:$E$336,$I$5,Dépenses!$J$6:$J$336,"2022",Dépenses!$I$6:$I$336,A9) -> 9436 | J9: =SUMIFS(Dépenses!$K$6:$K$336,Dépenses!F8:F338,$J$5,Dépenses!$J$6:$J$336,"2022",Dépenses!$I$6:$I$336,A9) -> 9635.18 | K9: =SUMIFS(Dépenses!$K$6:$K$336,Dépenses!$F$6:$F$336,$K$5,Dépenses!$J$6:$J$336,"2022",Dépenses!$I$6:$I$336,A9) -> 0 | L9: =SUM(I9:K9) -> 19071.18
A10: 4 | B10: Avril | C10: ='2022'!D161 - SUMIFS(Transfert!J7:J81,Transfert!F7:F81,"2022",Transfert!G7:G81,A10) -> 8940 | D10: =SUMIFS(Recettes!$J$6:$J$68,Recettes!$D$6:$D$68,$D$5,Recettes!$I$6:$I$68,"2022",Recettes!$H$6:$H$68,A10) -> 0 | E10: =SUMIFS(Recettes!$J$6:$J$68,Recettes!$F$6:$F$68,$E$5,Recettes!$I$6:$I$68,"2022",Recettes!$H$6:$H$68,A10) + SUMIFS(Transfert!J7:J81,Transfert!I7:I81,$E$5,Transfert!F7:F81,"2022",Transfert!G7:G81,A10) -> 7550 | F10: =SUMIFS(Recettes!$J$6:$J$68,Recettes!$F$6:$F$68,$F$5,Recettes!$I$6:$I$68,"2022",Recettes!$H$6:$H$68,A10) + SUMIFS(Transfert!K7:K81,Transfert!J7:J81,$F$5,Transfert!G7:G81,"2022",Transfert!H7:H81,A10) -> 0 | H10: Avril | I10: =SUMIFS(Dépenses!$K$6:$K$336,Dépenses!$E$6:$E$336,$I$5,Dépenses!$J$6:$J$336,"2022",Dépenses!$I$6:$I$336,A10) -> 12854 | J10: =SUMIFS(Dépenses!$K$6:$K$336,Dépenses!F9:F339,$J$5,Dépenses!$J$6:$J$336,"2022",Dépenses!$I$6:$I$336,A10) -> 12485.3 | K10: =SUMIFS(Dépenses!$K$6:$K$336,Dépenses!$F$6:$F$336,$K$5,Dépenses!$J$6:$J$336,"2022",Dépenses!$I$6:$I$336,A10) -> 0 | L10: =SUM(I10:K10) -> 25339.3
A11: 5 | B11: Mai | C11: ='2022'!D162 - SUMIFS(Transfert!J8:J82,Transfert!F8:F82,"2022",Transfert!G8:G82,A11) -> 9460 | D11: =SUMIFS(Recettes!$J$6:$J$68,Recettes!$D$6:$D$68,$D$5,Recettes!$I$6:$I$68,"2022",Recettes!$H$6:$H$68,A11) -> 3740 | E11: =SUMIFS(Recettes!$J$6:$J$68,Recettes!$F$6:$F$68,$E$5,Recettes!$I$6:$I$68,"2022",Recettes!$H$6:$H$68,A11) + SUMIFS(Transfert!J8:J82,Transfert!I8:I82,$E$5,Transfert!F8:F82,"2022",Transfert!G8:G82,A11) -> 5480 | F11: =SUMIFS(Recettes!$J$6:$J$68,Recettes!$F$6:$F$68,$F$5,Recettes!$I$6:$I$68,"2022",Recettes!$H$6:$H$68,A11) + SUMIFS(Transfert!K8:K81,Transfert!J8:J82,$F$5,Transfert!G8:G82,"2022",Transfert!H8:H82,A11) -> #VALUE! | H11: Mai | I11: =SUMIFS(Dépenses!$K$6:$K$336,Dépenses!$E$6:$E$336,$I$5,Dépenses!$J$6:$J$336,"2022",Dépenses!$I$6:$I$336,A11) -> 10821 | J11: =SUMIFS(Dépenses!$K$6:$K$336,Dépenses!F10:F340,$J$5,Dépenses!$J$6:$J$336,"2022",Dépenses!$I$6:$I$336,A11) -> 8725 | K11: =SUMIFS(Dépenses!$K$6:$K$336,Dépenses!$F$6:$F$336,$K$5,Dépenses!$J$6:$J$336,"2022",Dépenses!$I$6:$I$336,A11) -> 0 | L11: =SUM(I11:K11) -> 19546
A12: 6 | B12: Juin | C12: ='2022'!D163 - SUMIFS(Transfert!J9:J83,Transfert!F9:F83,"2022",Transfert!G9:G83,A12) -> 17390 | D12: =SUMIFS(Recettes!$J$6:$J$68,Recettes!$D$6:$D$68,$D$5,Recettes!$I$6:$I$68,"2022",Recettes!$H$6:$H$68,A12) -> 0 | E12: =SUMIFS(Recettes!$J$6:$J$68,Recettes!$F$6:$F$68,$E$5,Recettes!$I$6:$I$68,"2022",Recettes!$H$6:$H$68,A12) + SUMIFS(Transfert!J9:J83,Transfert!I9:I83,$E$5,Transfert!F9:F83,"2022",Transfert!G9:G83,A12) -> 3690 | F12: =SUMIFS(Recettes!$J$6:$J$68,Recettes!$F$6:$F$68,$F$5,Recettes!$I$6:$I$68,"2022",Recettes!$H$6:$H$68,A12) + SUMIFS(Transfert!K9:K81,Transfert!J9:J83,$F$5,Transfert!G9:G83,"2022",Transfert!H9:H83,A12) -> #VALUE! | H12: Juin | I12: =SUMIFS(Dépenses!$K$6:$K$336,Dépenses!$E$6:$E$336,$I$5,Dépenses!$J$6:$J$336,"2022",Dépenses!$I$6:$I$336,A12) -> 13523 | J12: =SUMIFS(Dépenses!$K$6:$K$336,Dépenses!F11:F341,$J$5,Dépenses!$J$6:$J$336,"2022",Dépenses!$I$6:$I$336,A12) -> 198 | K12: =SUMIFS(Dépenses!$K$6:$K$336,Dépenses!$F$6:$F$336,$K$5,Dépenses!$J$6:$J$336,"2022",Dépenses!$I$6:$I$336,A12) -> 0 | L12: =SUM(I12:K12) -> 13721
A13: 7 | B13: Juillet | C13: ='2022'!D164 - SUMIFS(Transfert!J10:J84,Transfert!F10:F84,"2022",Transfert!G10:G84,A13) -> 13330 | D13: =SUMIFS(Recettes!$J$6:$J$68,Recettes!$D$6:$D$68,$D$5,Recettes!$I$6:$I$68,"2022",Recettes!$H$6:$H$68,A13) -> 1870 | E13: =SUMIFS(Recettes!$J$6:$J$68,Recettes!$F$6:$F$68,$E$5,Recettes!$I$6:$I$68,"2022",Recettes!$H$6:$H$68,A13) + SUMIFS(Transfert!J10:J84,Transfert!I10:I84,$E$5,Transfert!F10:F84,"2022",Transfert!G10:G84,A13) -> 3500 | F13: =SUMIFS(Recettes!$J$6:$J$68,Recettes!$F$6:$F$68,$F$5,Recettes!$I$6:$I$68,"2022",Recettes!$H$6:$H$68,A13) + SUMIFS(Transfert!K10:K81,Transfert!J10:J84,$F$5,Transfert!G10:G84,"2022",Transfert!H10:H84,A13) -> #VALUE! | H13: Juillet | I13: =SUMIFS(Dépenses!$K$6:$K$336,Dépenses!$E$6:$E$336,$I$5,Dépenses!$J$6:$J$336,"2022",Dépenses!$I$6:$I$336,A13) -> 10960 | J13: =SUMIFS(Dépenses!$K$6:$K$336,Dépenses!F12:F342,$J$5,Dépenses!$J$6:$J$336,"2022",Dépenses!$I$6:$I$336,A13) -> 399 | K13: =SUMIFS(Dépenses!$K$6:$K$336,Dépenses!$F$6:$F$336,$K$5,Dépenses!$J$6:$J$336,"2022",Dépenses!$I$6:$I$336,A13) -> 0 | L13: =SUM(I13:K13) -> 11359
A14: 8 | B14: Août | C14: ='2022'!D165 - SUMIFS(Transfert!J11:J85,Transfert!F11:F85,"2022",Transfert!G11:G85,A14) -> 11030 | D14: =SUMIFS(Recettes!$J$6:$J$68,Recettes!$D$6:$D$68,$D$5,Recettes!$I$6:$I$68,"2022",Recettes!$H$6:$H$68,A14) -> 3929 | E14: =SUMIFS(Recettes!$J$6:$J$68,Recettes!$F$6:$F$68,$E$5,Recettes!$I$6:$I$68,"2022",Recettes!$H$6:$H$68,A14) + SUMIFS(Transfert!J11:J85,Transfert!I11:I85,$E$5,Transfert!F11:F85,"2022",Transfert!G11:G85,A14) -> 3500 | F14: =SUMIFS(Recettes!$J$6:$J$68,Recettes!$F$6:$F$68,$F$5,Recettes!$I$6:$I$68,"2022",Recettes!$H$6:$H$68,A14) + SUMIFS(Transfert!K11:K82,Transfert!J11:J85,$F$5,Transfert!G11:G85,"2022",Transfert!H11:H85,A14) -> #VALUE! | H14: Août | I14: =SUMIFS(Dépenses!$K$6:$K$336,Dépenses!$E$6:$E$336,$I$5,Dépenses!$J$6:$J$336,"2022",Dépenses!$I$6:$I$336,A14) -> 11241 | J14: =SUMIFS(Dépenses!$K$6:$K$336,Dépenses!F13:F343,$J$5,Dépenses!$J$6:$J$336,"2022",Dépenses!$I$6:$I$336,A14) -> 914 | K14: =SUMIFS(Dépenses!$K$6:$K$336,Dépenses!$F$6:$F$336,$K$5,Dépenses!$J$6:$J$336,"2022",Dépenses!$I$6:$I$336,A14) -> 0 | L14: =SUM(I14:K14) -> 12155
A15: 9 | B15: Sept | C15: ='2022'!D166 - SUMIFS(Transfert!J12:J86,Transfert!F12:F86,"2022",Transfert!G12:G86,A15) -> 13530 | D15: =SUMIFS(Recettes!$J$6:$J$68,Recettes!$D$6:$D$68,$D$5,Recettes!$I$6:$I$68,"2022",Recettes!$H$6:$H$68,A15) -> 5504 | E15: =SUMIFS(Recettes!$J$6:$J$68,Recettes!$F$6:$F$68,$E$5,Recettes!$I$6:$I$68,"2022",Recettes!$H$6:$H$68,A15) + SUMIFS(Transfert!J12:J86,Transfert!I12:I86,$E$5,Transfert!F12:F86,"2022",Transfert!G12:G86,A15) -> 3500 | F15: =SUMIFS(Recettes!$J$6:$J$68,Recettes!$F$6:$F$68,$F$5,Recettes!$I$6:$I$68,"2022",Recettes!$H$6:$H$68,A15) + SUMIFS(Transfert!K12:K83,Transfert!J12:J86,$F$5,Transfert!G12:G86,"2022",Transfert!H12:H86,A15) -> #VALUE! | H15: Sept | I15: =SUMIFS(Dépenses!$K$6:$K$336,Dépenses!$E$6:$E$336,$I$5,Dépenses!$J$6:$J$336,"2022",Dépenses!$I$6:$I$336,A15) -> 10538 | J15: =SUMIFS(Dépenses!$K$6:$K$336,Dépenses!F14:F344,$J$5,Dépenses!$J$6:$J$336,"2022",Dépenses!$I$6:$I$336,A15) -> 4577 | K15: =SUMIFS(Dépenses!$K$6:$K$336,Dépenses!$F$6:$F$336,$K$5,Dépenses!$J$6:$J$336,"2022",Dépenses!$I$6:$I$336,A15) -> 0 | L15: =SUM(I15:K15) -> 15115
A16: 10 | B16: Oct | C16: ='2022'!D167 - SUMIFS(Transfert!J13:J87,Transfert!F13:F87,"2022",Transfert!G13:G87,A16) -> 13930 | D16: =SUMIFS(Recettes!$J$6:$J$68,Recettes!$D$6:$D$68,$D$5,Recettes!$I$6:$I$68,"2022",Recettes!$H$6:$H$68,A16) -> 452 | E16: =SUMIFS(Recettes!$J$6:$J$68,Recettes!$F$6:$F$68,$E$5,Recettes!$I$6:$I$68,"2022",Recettes!$H$6:$H$68,A16) + SUMIFS(Transfert!J13:J87,Transfert!I13:I87,$E$5,Transfert!F13:F87,"2022",Transfert!G13:G87,A16) -> 3500 | F16: =SUMIFS(Recettes!$J$6:$J$68,Recettes!$F$6:$F$68,$F$5,Recettes!$I$6:$I$68,"2022",Recettes!$H$6:$H$68,A16) + SUMIFS(Transfert!K13:K84,Transfert!J13:J87,$F$5,Transfert!G13:G87,"2022",Transfert!H13:H87,A16) -> #VALUE! | H16: Oct | I16: =SUMIFS(Dépenses!$K$6:$K$336,Dépenses!$E$6:$E$336,$I$5,Dépenses!$J$6:$J$336,"2022",Dépenses!$I$6:$I$336,A16) -> 10814 | J16: =SUMIFS(Dépenses!$K$6:$K$336,Dépenses!F15:F345,$J$5,Dépenses!$J$6:$J$336,"2022",Dépenses!$I$6:$I$336,A16) -> 6059.27 | K16: =SUMIFS(Dépenses!$K$6:$K$336,Dépenses!$F$6:$F$336,$K$5,Dépenses!$J$6:$J$336,"2022",Dépenses!$I$6:$I$336,A16) -> 21960 | L16: =SUM(I16:K16) -> 38833.27
A17: 11 | B17: Nov | C17: ='2022'!D168 - SUMIFS(Transfert!J14:J88,Transfert!F14:F88,"2022",Transfert!G14:G88,A17) -> 10900 | D17: =SUMIFS(Recettes!$J$6:$J$68,Recettes!$D$6:$D$68,$D$5,Recettes!$I$6:$I$68,"2022",Recettes!$H$6:$H$68,A17) -> 368 | E17: =SUMIFS(Recettes!$J$6:$J$68,Recettes!$F$6:$F$68,$E$5,Recettes!$I$6:$I$68,"2022",Recettes!$H$6:$H$68,A17) + SUMIFS(Transfert!J14:J88,Transfert!I14:I88,$E$5,Transfert!F14:F88,"2022",Transfert!G14:G88,A17) -> 3500 | F17: =SUMIFS(Recettes!$J$6:$J$68,Recettes!$F$6:$F$68,$F$5,Recettes!$I$6:$I$68,"2022",Recettes!$H$6:$H$68,A17) + SUMIFS(Transfert!K14:K85,Transfert!J14:J88,$F$5,Transfert!G14:G88,"2022",Transfert!H14:H88,A17) -> #VALUE! | H17: Nov | I17: =SUMIFS(Dépenses!$K$6:$K$336,Dépenses!$E$6:$E$336,$I$5,Dépenses!$J$6:$J$336,"2022",Dépenses!$I$6:$I$336,A17) -> 10015 | J17: =SUMIFS(Dépenses!$K$6:$K$336,Dépenses!F16:F346,$J$5,Dépenses!$J$6:$J$336,"2022",Dépenses!$I$6:$I$336,A17) -> 3590.99 | K17: =SUMIFS(Dépenses!$K$6:$K$336,Dépenses!$F$6:$F$336,$K$5,Dépenses!$J$6:$J$336,"2022",Dépenses!$I$6:$I$336,A17) -> 0 | L17: =SUM(I17:K17) -> 13605.99
A18: 12 | B18: Déc | C18: ='2022'!D169 - SUMIFS(Transfert!J15:J89,Transfert!F15:F89,"2022",Transfert!G15:G89,A18) -> 17629 | D18: =SUMIFS(Recettes!$J$6:$J$68,Recettes!$D$6:$D$68,$D$5,Recettes!$I$6:$I$68,"2022",Recettes!$H$6:$H$68,A18) -> 2274 | E18: =SUMIFS(Recettes!$J$6:$J$68,Recettes!$F$6:$F$68,$E$5,Recettes!$I$6:$I$68,"2022",Recettes!$H$6:$H$68,A18) + SUMIFS(Transfert!J15:J89,Transfert!I15:I89,$E$5,Transfert!F15:F89,"2022",Transfert!G15:G89,A18) -> 3500 | F18: =SUMIFS(Recettes!$J$6:$J$68,Recettes!$F$6:$F$68,$F$5,Recettes!$I$6:$I$68,"2022",Recettes!$H$6:$H$68,A18) + SUMIFS(Transfert!K15:K86,Transfert!J15:J89,$F$5,Transfert!G15:G89,"2022",Transfert!H15:H89,A18) -> #VALUE! | H18: Déc | I18: =SUMIFS(Dépenses!$K$6:$K$336,Dépenses!$E$6:$E$336,$I$5,Dépenses!$J$6:$J$336,"2022",Dépenses!$I$6:$I$336,A18) -> 11825 | J18: =SUMIFS(Dépenses!$K$6:$K$336,Dépenses!F17:F347,$J$5,Dépenses!$J$6:$J$336,"2022",Dépenses!$I$6:$I$336,A18) -> 1064 | K18: =SUMIFS(Dépenses!$K$6:$K$336,Dépenses!$F$6:$F$336,$K$5,Dépenses!$J$6:$J$336,"2022",Dépenses!$I$6:$I$336,A18) -> 0 | L18: =SUM(I18:K18) -> 12889
B19: TOTAL | C19: =SUM(C7:C18) -> 157919 | D19: =SUM(D7:D18) -> 22837 | E19: =SUM(E7:E18) -> 65280 | F19: =SUM(F7:F18) -> #VALUE! | G19: =+D19+#REF!+#REF!+F19 -> #REF! | H19: TOTAL | I19: =SUM(I7:I18) -> 132287 | J19: =SUM(J7:J18) -> 61764.7 | K19: =SUM(K7:K18) -> 21960 | L19: =SUM(I19:K19) -> 216011.7
B20: SOLDE 2022 | G20: =+G6+G19 -> #REF! | L20: =+L6+L19 -> 216011.7
B21: RECETTES -DEPENSES 2019-2020-2021 : (154394,00)-(102322,00) = | L21: =+G20-L20 -> #REF!

Sheet Config
A1: Type de Recette | C1: Mode Recette | F1: Année | H1: Journal Types | J1: Paie & Primes & CNSS | K1: Téléphonie & Electricité | L1: Dépenses Courantes | M1: Transfert | N1: Travaux | O1: Entretien Espaces Verts
A2: Loyer Appart | C2: Espèce | F2: 2022 | H2: Paie & Primes & CNSS | J2: Paie Personnel | K2: Redal | L2: Produits d'entretien | M2: Transfert SG Caisse | N2: Travaux de Maçonnerie | O2: Materiel/ pièces rechange
A3: Loyer Garage | C3: Chèque | F3: 2023 | H3: Travaux | J3: Primes Annuelles - Aid Al Adha | K3: Inwi | L3: Plomberie | M3: Transfert Chaabi Caisse | N3: Peinture Extérieure des Immeubles | O3: Essence - Huile
A4: Loyer Economat | C4: Virement | H4: Téléphonie & Electricité | J4: Primes Annuelles - Aid El Fitr | L4: Entretien Electricité | N4: Participation Syndic aux Trx des Im: | O4: Plantations
A5: Eléctricité Garage | C5: Agios | H5: Dépenses Courantes | J5: Prélèvement CNSS | L5: Divers | N5: Divers | O5: Installation de pompage
A6: Electricité Economat | C6: Prélèvement | H6: Entretien Espaces Verts
H7: Transfert

Sheet Récap 2022 (2)
B1: SITUATION 2022
F2: =SUMIFS(Transfert!J4:J81,Transfert!I4:I81,$E$5,Transfert!F4:F81,"2022",Transfert!G4:G81,A7) -> 6350
B3: RECETTES | H3: DEPENSES
C4: Caisse | E4: Banque | I4: Paie Personnel | J4: Prélèvement CNSS | K4: Primes Annuelles | L4: Redal | M4: Inwi | N4: Entretien Electricité | O4: Essence - Huile | P4: installation de pompage | Q4: Materiel/ pièces rechange | R4: Peinture Extérieure des Immeubles | T4: Plantations | U4: Plomberie | V4: Produits d'entretien | W4: Travaux de Maçonnerie
B5: MOIS | C5: Cotisations | D5: Espèce | E5: BP | F5: TGR | G5: TOTAL | H5: MOIS | I5: Espèce | J5: Prélèvement | K5: Espèce | L5: Chèque | M5: Prélèvement | N5: Espèce | O5: Espèce | P5: Espèce | Q5: Espèce | R5: Espèce | S5: Chèque | T5: Espèce | U5: Espèce | V5: Espèce | W5: Chèque | X5: TOTAL
B6: REPORT: | G6: =+'[1]RECETTES 19 20 21'!Q75 -> 27235.72
A7: 1 | B7: Janv | C7: ='2022'!D158 - SUMIFS(Transfert!J4:J81,Transfert!F4:F81,"2022",Transfert!G4:G81,A7) -> 11730 | D7: =SUMIFS(Recettes!$J$6:$J$68,Recettes!$D$6:$D$68,$D$5,Recettes!$I$6:$I$68,"2022",Recettes!$H$6:$H$68,A7) -> 0 | E7: =SUMIFS(Recettes!$J$6:$J$68,Recettes!$F$6:$F$68,$E$5,Recettes!$I$6:$I$68,"2022",Recettes!$H$6:$H$68,A7) + SUMIFS(Transfert!J4:J81,Transfert!I4:I81,$E$5,Transfert!F4:F81,"2022",Transfert!G4:G81,A7) -> 9850 | F7: =SUMIFS(Recettes!$J$6:$J$68,Recettes!$F$6:$F$68,$F$5,Recettes!$I$6:$I$68,"2022",Recettes!$H$6:$H$68,A7) + SUMIFS(Transfert!K4:K81,Transfert!J4:J81,$F$5,Transfert!G4:G81,"2022",Transfert!H4:H81,A7) -> 0 | H7: Janv | I7: =SUMIFS(Dépenses!$K$6:$K$336,Dépenses!$E$6:$E$336,$I$5,Dépenses!$J$6:$J$336,"2022",Dépenses!$I$6:$I$336,A7,Dépenses!$C$6:$C$336,$I$4) -> 8700 | J7: =SUMIFS(Dépenses!$K$6:$K$336,Dépenses!$E$6:$E$336,$J$5,Dépenses!$J$6:$J$336,"2022",Dépenses!$I$6:$I$336,A7,Dépenses!$C$6:$C$336,$J$4) -> 0 | K7: =SUMIFS(Dépenses!$K$6:$K$336,Dépenses!$C$6:$C$336,"Primes Annuelles - Aid El Fitr",Dépenses!$J$6:$J$336,"2022",Dépenses!$I$6:$I$336,A7) + SUMIFS(Dépenses!$K$6:$K$336,Dépenses!$C$6:$C$336,"Primes Annuelles - Aid Al Adha",Dépenses!$J$6:$J$336,"2022",Dépenses!$I$6:$I$336,A7) -> 0 | L7: =SUMIFS(Dépenses!$K$6:$K$336,Dépenses!$E$6:$E$336,$L$5,Dépenses!$J$6:$J$336,"2022",Dépenses!$I$6:$I$336,A7,Dépenses!$C$6:$C$336,$L$4) -> 963.96 | M7: =SUMIFS(Dépenses!$K$6:$K$336,Dépenses!$E$6:$E$336,$M$5,Dépenses!$J$6:$J$336,"2022",Dépenses!$I$6:$I$336,A7,Dépenses!$C$6:$C$336,$M$4) -> 199 | N7: =SUMIFS(Dépenses!$K$6:$K$336,Dépenses!$E$6:$E$336,$N$5,Dépenses!$J$6:$J$336,"2022",Dépenses!$I$6:$I$336,A7,Dépenses!$C$6:$C$336,$N$4) -> 255 | O7: =SUMIFS(Dépenses!$K$6:$K$336,Dépenses!$E$6:$E$336,$O$5,Dépenses!$J$6:$J$336,"2022",Dépenses!$I$6:$I$336,A7,Dépenses!$C$6:$C$336,$O$4) -> 0 | P7: =SUMIFS(Dépenses!$K$6:$K$336,Dépenses!$E$6:$E$336,$P$5,Dépenses!$J$6:$J$336,"2022",Dépenses!$I$6:$I$336,A7,Dépenses!$C$6:$C$336,$P$4) -> 0 | Q7: =SUMIFS(Dépenses!$K$6:$K$336,Dépenses!$E$6:$E$336,$Q$5,Dépenses!$J$6:$J$336,"2022",Dépenses!$I$6:$I$336,A7,Dépenses!$C$6:$C$336,$Q$4) -> 0 | R7: =SUMIFS(Dépenses!$K$6:$K$336,Dépenses!$E$6:$E$336,$R$5,Dépenses!$J$6:$J$336,"2022",Dépenses!$I$6:$I$336,A7,Dépenses!$C$6:$C$336,$R$4) -> 0 | S7: =SUMIFS(Dépenses!$K$6:$K$336,Dépenses!$E$6:$E$336,$S$5,Dépenses!$J$6:$J$336,"2022",Dépenses!$I$6:$I$336,A7,Dépenses!$C$6:$C$336,$R$4) -> 0 | T7: =SUMIFS(Dépenses!$K$6:$K$336,Dépenses!$E$6:$E$336,$T$5,Dépenses!$J$6:$J$336,"2022",Dépenses!$I$6:$I$336,A7,Dépenses!$C$6:$C$336,$T$4) -> 0 | U7: =SUMIFS(Dépenses!$K$6:$K$336,Dépenses!$E$6:$E$336,$U$5,Dépenses!$J$6:$J$336,"2022",Dépenses!$I$6:$I$336,A7,Dépenses!$C$6:$C$336,$U$4) -> 0 | V7: =SUMIFS(Dépenses!$K$6:$K$336,Dépenses!$E$6:$E$336,$V$5,Dépenses!$J$6:$J$336,"2022",Dépenses!$I$6:$I$336,A7,Dépenses!$C$6:$C$336,$V$4) -> 118 | W7: =SUMIFS(Dépenses!$K$6:$K$336,Dépenses!$E$6:$E$336,$W$5,Dépenses!$J$6:$J$336,"2022",Dépenses!$I$6:$I$336,A7,Dépenses!$C$6:$C$336,$W$4) -> 12384 | X7: =SUM(I7:W7) -> 22619.96
A8: 2 | B8: Fev | C8: ='2022'!D159 - SUMIFS(Transfert!J5:J81,Transfert!F5:F81,"2022",Transfert!G5:G81,A8) -> 12950 | D8: =SUMIFS(Recettes!$J$6:$J$68,Recettes!$D$6:$D$68,$D$5,Recettes!$I$6:$I$68,"2022",Recettes!$H$6:$H$68,A8) -> 2830 | E8: =SUMIFS(Recettes!$J$6:$J$68,Recettes!$F$6:$F$68,$E$5,Recettes!$I$6:$I$68,"2022",Recettes!$H$6:$H$68,A8) + SUMIFS(Transfert!J5:J81,Transfert!I5:I81,$E$5,Transfert!F5:F81,"2022",Transfert!G5:G81,A8) -> 11330 | F8: =SUMIFS(Recettes!$J$6:$J$68,Recettes!$F$6:$F$68,$F$5,Recettes!$I$6:$I$68,"2022",Recettes!$H$6:$H$68,A8) + SUMIFS(Transfert!K5:K81,Transfert!J5:J81,$F$5,Transfert!G5:G81,"2022",Transfert!H5:H81,A8) -> 0 | H8: Fev | I8: =SUMIFS(Dépenses!$K$6:$K$336,Dépenses!$E$6:$E$336,$I$5,Dépenses!$J$6:$J$336,"2022",Dépenses!$I$6:$I$336,A8,Dépenses!$C$6:$C$336,$I$4) -> 9620 | J8: =SUMIFS(Dépenses!$K$6:$K$336,Dépenses!$E$6:$E$336,$J$5,Dépenses!$J$6:$J$336,"2022",Dépenses!$I$6:$I$336,A8,Dépenses!$C$6:$C$336,$J$4) -> 1885.72 | K8: =SUMIFS(Dépenses!$K$6:$K$336,Dépenses!$C$6:$C$336,"Primes Annuelles - Aid El Fitr",Dépenses!$J$6:$J$336,"2022",Dépenses!$I$6:$I$336,A8) + SUMIFS(Dépenses!$K$6:$K$336,Dépenses!$C$6:$C$336,"Primes Annuelles - Aid Al Adha",Dépenses!$J$6:$J$336,"2022",Dépenses!$I$6:$I$336,A8) -> 0 | L8: =SUMIFS(Dépenses!$K$6:$K$336,Dépenses!$E$6:$E$336,$L$5,Dépenses!$J$6:$J$336,"2022",Dépenses!$I$6:$I$336,A8,Dépenses!$C$6:$C$336,$L$4) -> 729.64 | M8: =SUMIFS(Dépenses!$K$6:$K$336,Dépenses!$E$6:$E$336,$M$5,Dépenses!$J$6:$J$336,"2022",Dépenses!$I$6:$I$336,A8,Dépenses!$C$6:$C$336,$M$4) -> 199 | N8: =SUMIFS(Dépenses!$K$6:$K$336,Dépenses!$E$6:$E$336,$N$5,Dépenses!$J$6:$J$336,"2022",Dépenses!$I$6:$I$336,A8,Dépenses!$C$6:$C$336,$N$4) -> 0 | O8: =SUMIFS(Dépenses!$K$6:$K$336,Dépenses!$E$6:$E$336,$O$5,Dépenses!$J$6:$J$336,"2022",Dépenses!$I$6:$I$336,A8,Dépenses!$C$6:$C$336,$O$4) -> 50 | P8: =SUMIFS(Dépenses!$K$6:$K$336,Dépenses!$E$6:$E$336,$P$5,Dépenses!$J$6:$J$336,"2022",Dépenses!$I$6:$I$336,A8,Dépenses!$C$6:$C$336,$P$4) -> 0 | Q8: =SUMIFS(Dépenses!$K$6:$K$336,Dépenses!$E$6:$E$336,$Q$5,Dépenses!$J$6:$J$336,"2022",Dépenses!$I$6:$I$336,A8,Dépenses!$C$6:$C$336,$Q$4) -> 0 | R8: =SUMIFS(Dépenses!$K$6:$K$336,Dépenses!$E$6:$E$336,$R$5,Dépenses!$J$6:$J$336,"2022",Dépenses!$I$6:$I$336,A8,Dépenses!$C$6:$C$336,$R$4) -> 0 | S8: =SUMIFS(Dépenses!$K$6:$K$336,Dépenses!$E$6:$E$336,$S$5,Dépenses!$J$6:$J$336,"2022",Dépenses!$I$6:$I$336,A8,Dépenses!$C$6:$C$336,$R$4) -> 0 | T8: =SUMIFS(Dépenses!$K$6:$K$336,Dépenses!$E$6:$E$336,$T$5,Dépenses!$J$6:$J$336,"2022",Dépenses!$I$6:$I$336,A8,Dépenses!$C$6:$C$336,$T$4) -> 0 | U8: =SUMIFS(Dépenses!$K$6:$K$336,Dépenses!$E$6:$E$336,$U$5,Dépenses!$J$6:$J$336,"2022",Dépenses!$I$6:$I$336,A8,Dépenses!$C$6:$C$336,$U$4) -> 0 | V8: =SUMIFS(Dépenses!$K$6:$K$336,Dépenses!$E$6:$E$336,$V$5,Dépenses!$J$6:$J$336,"2022",Dépenses!$I$6:$I$336,A8,Dépenses!$C$6:$C$336,$V$4) -> 45 | W8: =SUMIFS(Dépenses!$K$6:$K$336,Dépenses!$E$6:$E$336,$W$5,Dépenses!$J$6:$J$336,"2022",Dépenses!$I$6:$I$336,A8,Dépenses!$C$6:$C$336,$W$4) -> 0 | X8: =SUM(I8:W8) -> 12529.36
A9: 3 | B9: Mars | C9: ='2022'!D160 - SUMIFS(Transfert!J6:J81,Transfert!F6:F81,"2022",Transfert!G6:G81,A9) -> 17100 | D9: =SUMIFS(Recettes!$J$6:$J$68,Recettes!$D$6:$D$68,$D$5,Recettes!$I$6:$I$68,"2022",Recettes!$H$6:$H$68,A9) -> 1870 | E9: =SUMIFS(Recettes!$J$6:$J$68,Recettes!$F$6:$F$68,$E$5,Recettes!$I$6:$I$68,"2022",Recettes!$H$6:$H$68,A9) + SUMIFS(Transfert!J6:J81,Transfert!I6:I81,$E$5,Transfert!F6:F81,"2022",Transfert!G6:G81,A9) -> 6380 | F9: =SUMIFS(Recettes!$J$6:$J$68,Recettes!$F$6:$F$68,$F$5,Recettes!$I$6:$I$68,"2022",Recettes!$H$6:$H$68,A9) + SUMIFS(Transfert!K6:K81,Transfert!J6:J81,$F$5,Transfert!G6:G81,"2022",Transfert!H6:H81,A9) -> 0 | H9: Mars | I9: =SUMIFS(Dépenses!$K$6:$K$336,Dépenses!$E$6:$E$336,$I$5,Dépenses!$J$6:$J$336,"2022",Dépenses!$I$6:$I$336,A9,Dépenses!$C$6:$C$336,$I$4) -> 8700 | J9: =SUMIFS(Dépenses!$K$6:$K$336,Dépenses!$E$6:$E$336,$J$5,Dépenses!$J$6:$J$336,"2022",Dépenses!$I$6:$I$336,A9,Dépenses!$C$6:$C$336,$J$4) -> 2514.3 | K9: =SUMIFS(Dépenses!$K$6:$K$336,Dépenses!$C$6:$C$336,"Primes Annuelles - Aid El Fitr",Dépenses!$J$6:$J$336,"2022",Dépenses!$I$6:$I$336,A9) + SUMIFS(Dépenses!$K$6:$K$336,Dépenses!$C$6:$C$336,"Primes Annuelles - Aid Al Adha",Dépenses!$J$6:$J$336,"2022",Dépenses!$I$6:$I$336,A9) -> 0 | L9: =SUMIFS(Dépenses!$K$6:$K$336,Dépenses!$E$6:$E$336,$L$5,Dépenses!$J$6:$J$336,"2022",Dépenses!$I$6:$I$336,A9,Dépenses!$C$6:$C$336,$L$4) -> 831.18 | M9: =SUMIFS(Dépenses!$K$6:$K$336,Dépenses!$E$6:$E$336,$M$5,Dépenses!$J$6:$J$336,"2022",Dépenses!$I$6:$I$336,A9,Dépenses!$C$6:$C$336,$M$4) -> 199 | N9: =SUMIFS(Dépenses!$K$6:$K$336,Dépenses!$E$6:$E$336,$N$5,Dépenses!$J$6:$J$336,"2022",Dépenses!$I$6:$I$336,A9,Dépenses!$C$6:$C$336,$N$4) -> 60 | O9: =SUMIFS(Dépenses!$K$6:$K$336,Dépenses!$E$6:$E$336,$O$5,Dépenses!$J$6:$J$336,"2022",Dépenses!$I$6:$I$336,A9,Dépenses!$C$6:$C$336,$O$4) -> 44 | P9: =SUMIFS(Dépenses!$K$6:$K$336,Dépenses!$E$6:$E$336,$P$5,Dépenses!$J$6:$J$336,"2022",Dépenses!$I$6:$I$336,A9,Dépenses!$C$6:$C$336,$P$4) -> 0 | Q9: =SUMIFS(Dépenses!$K$6:$K$336,Dépenses!$E$6:$E$336,$Q$5,Dépenses!$J$6:$J$336,"2022",Dépenses!$I$6:$I$336,A9,Dépenses!$C$6:$C$336,$Q$4) -> 0 | R9: =SUMIFS(Dépenses!$K$6:$K$336,Dépenses!$E$6:$E$336,$R$5,Dépenses!$J$6:$J$336,"2022",Dépenses!$I$6:$I$336,A9,Dépenses!$C$6:$C$336,$R$4) -> 0 | S9: =SUMIFS(Dépenses!$K$6:$K$336,Dépenses!$E$6:$E$336,$S$5,Dépenses!$J$6:$J$336,"2022",Dépenses!$I$6:$I$336,A9,Dépenses!$C$6:$C$336,$R$4) -> 0 | T9: =SUMIFS(Dépenses!$K$6:$K$336,Dépenses!$E$6:$E$336,$T$5,Dépenses!$J$6:$J$336,"2022",Dépenses!$I$6:$I$336,A9,Dépenses!$C$6:$C$336,$T$4) -> 0 | U9: =SUMIFS(Dépenses!$K$6:$K$336,Dépenses!$E$6:$E$336,$U$5,Dépenses!$J$6:$J$336,"2022",Dépenses!$I$6:$I$336,A9,Dépenses!$C$6:$C$336,$U$4) -> 0 | V9: =SUMIFS(Dépenses!$K$6:$K$336,Dépenses!$E$6:$E$336,$V$5,Dépenses!$J$6:$J$336,"2022",Dépenses!$I$6:$I$336,A9,Dépenses!$C$6:$C$336,$V$4) -> 262 | W9: =SUMIFS(Dépenses!$K$6:$K$336,Dépenses!$E$6:$E$336,$W$5,Dépenses!$J$6:$J$336,"2022",Dépenses!$I$6:$I$336,A9,Dépenses!$C$6:$C$336,$W$4) -> 20420 | X9: =SUM(I9:W9) -> 33030.48
A10: 4 | B10: Avril | C10: ='2022'!D161 - SUMIFS(Transfert!J7:J81,Transfert!F7:F81,"2022",Transfert!G7:G81,A10) -> 8940 | D10: =SUMIFS(Recettes!$J$6:$J$68,Recettes!$D$6:$D$68,$D$5,Recettes!$I$6:$I$68,"2022",Recettes!$H$6:$H$68,A10) -> 0 | E10: =SUMIFS(Recettes!$J$6:$J$68,Recettes!$F$6:$F$68,$E$5,Recettes!$I$6:$I$68,"2022",Recettes!$H$6:$H$68,A10) + SUMIFS(Transfert!J7:J81,Transfert!I7:I81,$E$5,Transfert!F7:F81,"2022",Transfert!G7:G81,A10) -> 7550 | F10: =SUMIFS(Recettes!$J$6:$J$68,Recettes!$F$6:$F$68,$F$5,Recettes!$I$6:$I$68,"2022",Recettes!$H$6:$H$68,A10) + SUMIFS(Transfert!K7:K81,Transfert!J7:J81,$F$5,Transfert!G7:G81,"2022",Transfert!H7:H81,A10) -> 0 | H10: Avril | I10: =SUMIFS(Dépenses!$K$6:$K$336,Dépenses!$E$6:$E$336,$I$5,Dépenses!$J$6:$J$336,"2022",Dépenses!$I$6:$I$336,A10,Dépenses!$C$6:$C$336,$I$4) -> 8700 | J10: =SUMIFS(Dépenses!$K$6:$K$336,Dépenses!$E$6:$E$336,$J$5,Dépenses!$J$6:$J$336,"2022",Dépenses!$I$6:$I$336,A10,Dépenses!$C$6:$C$336,$J$4) -> 2514.3 | K10: =SUMIFS(Dépenses!$K$6:$K$336,Dépenses!$C$6:$C$336,"Primes Annuelles - Aid El Fitr",Dépenses!$J$6:$J$336,"2022",Dépenses!$I$6:$I$336,A10) + SUMIFS(Dépenses!$K$6:$K$336,Dépenses!$C$6:$C$336,"Primes Annuelles - Aid Al Adha",Dépenses!$J$6:$J$336,"2022",Dépenses!$I$6:$I$336,A10) -> 1200 | L10: =SUMIFS(Dépenses!$K$6:$K$336,Dépenses!$E$6:$E$336,$L$5,Dépenses!$J$6:$J$336,"2022",Dépenses!$I$6:$I$336,A10,Dépenses!$C$6:$C$336,$L$4) -> 865.07 | M10: =SUMIFS(Dépenses!$K$6:$K$336,Dépenses!$E$6:$E$336,$M$5,Dépenses!$J$6:$J$336,"2022",Dépenses!$I$6:$I$336,A10,Dépenses!$C$6:$C$336,$M$4) -> 199 | N10: =SUMIFS(Dépenses!$K$6:$K$336,Dépenses!$E$6:$E$336,$N$5,Dépenses!$J$6:$J$336,"2022",Dépenses!$I$6:$I$336,A10,Dépenses!$C$6:$C$336,$N$4) -> 168 | O10: =SUMIFS(Dépenses!$K$6:$K$336,Dépenses!$E$6:$E$336,$O$5,Dépenses!$J$6:$J$336,"2022",Dépenses!$I$6:$I$336,A10,Dépenses!$C$6:$C$336,$O$4) -> 40 | P10: =SUMIFS(Dépenses!$K$6:$K$336,Dépenses!$E$6:$E$336,$P$5,Dépenses!$J$6:$J$336,"2022",Dépenses!$I$6:$I$336,A10,Dépenses!$C$6:$C$336,$P$4) -> 1000 | Q10: =SUMIFS(Dépenses!$K$6:$K$336,Dépenses!$E$6:$E$336,$Q$5,Dépenses!$J$6:$J$336,"2022",Dépenses!$I$6:$I$336,A10,Dépenses!$C$6:$C$336,$Q$4) -> 50 | R10: =SUMIFS(Dépenses!$K$6:$K$336,Dépenses!$E$6:$E$336,$R$5,Dépenses!$J$6:$J$336,"2022",Dépenses!$I$6:$I$336,A10,Dépenses!$C$6:$C$336,$R$4) -> 0 | S10: =SUMIFS(Dépenses!$K$6:$K$336,Dépenses!$E$6:$E$336,$S$5,Dépenses!$J$6:$J$336,"2022",Dépenses!$I$6:$I$336,A10,Dépenses!$C$6:$C$336,$R$4) -> 0 | T10: =SUMIFS(Dépenses!$K$6:$K$336,Dépenses!$E$6:$E$336,$T$5,Dépenses!$J$6:$J$336,"2022",Dépenses!$I$6:$I$336,A10,Dépenses!$C$6:$C$336,$T$4) -> 0 | U10: =SUMIFS(Dépenses!$K$6:$K$336,Dépenses!$E$6:$E$336,$U$5,Dépenses!$J$6:$J$336,"2022",Dépenses!$I$6:$I$336,A10,Dépenses!$C$6:$C$336,$U$4) -> 1400 | V10: =SUMIFS(Dépenses!$K$6:$K$336,Dépenses!$E$6:$E$336,$V$5,Dépenses!$J$6:$J$336,"2022",Dépenses!$I$6:$I$336,A10,Dépenses!$C$6:$C$336,$V$4) -> 136 | W10: =SUMIFS(Dépenses!$K$6:$K$336,Dépenses!$E$6:$E$336,$W$5,Dépenses!$J$6:$J$336,"2022",Dépenses!$I$6:$I$336,A10,Dépenses!$C$6:$C$336,$W$4) -> 0 | X10: =SUM(I10:W10) -> 16272.37
A11: 5 | B11: Mai | C11: ='2022'!D162 - SUMIFS(Transfert!J8:J82,Transfert!F8:F82,"2022",Transfert!G8:G82,A11) -> 9460 | D11: =SUMIFS(Recettes!$J$6:$J$68,Recettes!$D$6:$D$68,$D$5,Recettes!$I$6:$I$68,"2022",Recettes!$H$6:$H$68,A11) -> 3740 | E11: =SUMIFS(Recettes!$J$6:$J$68,Recettes!$F$6:$F$68,$E$5,Recettes!$I$6:$I$68,"2022",Recettes!$H$6:$H$68,A11) + SUMIFS(Transfert!J8:J82,Transfert!I8:I82,$E$5,Transfert!F8:F82,"2022",Transfert!G8:G82,A11) -> 5480 | F11: =SUMIFS(Recettes!$J$6:$J$68,Recettes!$F$6:$F$68,$F$5,Recettes!$I$6:$I$68,"2022",Recettes!$H$6:$H$68,A11) + SUMIFS(Transfert!K8:K81,Transfert!J8:J82,$F$5,Transfert!G8:G82,"2022",Transfert!H8:H82,A11) -> #VALUE! | H11: Mai | I11: =SUMIFS(Dépenses!$K$6:$K$336,Dépenses!$E$6:$E$336,$I$5,Dépenses!$J$6:$J$336,"2022",Dépenses!$I$6:$I$336,A11,Dépenses!$C$6:$C$336,$I$4) -> 8700 | J11: =SUMIFS(Dépenses!$K$6:$K$336,Dépenses!$E$6:$E$336,$J$5,Dépenses!$J$6:$J$336,"2022",Dépenses!$I$6:$I$336,A11,Dépenses!$C$6:$C$336,$J$4) -> 2514.3 | K11: =SUMIFS(Dépenses!$K$6:$K$336,Dépenses!$C$6:$C$336,"Primes Annuelles - Aid El Fitr",Dépenses!$J$6:$J$336,"2022",Dépenses!$I$6:$I$336,A11) + SUMIFS(Dépenses!$K$6:$K$336,Dépenses!$C$6:$C$336,"Primes Annuelles - Aid Al Adha",Dépenses!$J$6:$J$336,"2022",Dépenses!$I$6:$I$336,A11) -> 0 | L11: =SUMIFS(Dépenses!$K$6:$K$336,Dépenses!$E$6:$E$336,$L$5,Dépenses!$J$6:$J$336,"2022",Dépenses!$I$6:$I$336,A11,Dépenses!$C$6:$C$336,$L$4) -> 748.71 | M11: =SUMIFS(Dépenses!$K$6:$K$336,Dépenses!$E$6:$E$336,$M$5,Dépenses!$J$6:$J$336,"2022",Dépenses!$I$6:$I$336,A11,Dépenses!$C$6:$C$336,$M$4) -> 199 | N11: =SUMIFS(Dépenses!$K$6:$K$336,Dépenses!$E$6:$E$336,$N$5,Dépenses!$J$6:$J$336,"2022",Dépenses!$I$6:$I$336,A11,Dépenses!$C$6:$C$336,$N$4) -> 216 | O11: =SUMIFS(Dépenses!$K$6:$K$336,Dépenses!$E$6:$E$336,$O$5,Dépenses!$J$6:$J$336,"2022",Dépenses!$I$6:$I$336,A11,Dépenses!$C$6:$C$336,$O$4) -> 135 | P11: =SUMIFS(Dépenses!$K$6:$K$336,Dépenses!$E$6:$E$336,$P$5,Dépenses!$J$6:$J$336,"2022",Dépenses!$I$6:$I$336,A11,Dépenses!$C$6:$C$336,$P$4) -> 0 | Q11: =SUMIFS(Dépenses!$K$6:$K$336,Dépenses!$E$6:$E$336,$Q$5,Dépenses!$J$6:$J$336,"2022",Dépenses!$I$6:$I$336,A11,Dépenses!$C$6:$C$336,$Q$4) -> 0 | R11: =SUMIFS(Dépenses!$K$6:$K$336,Dépenses!$E$6:$E$336,$R$5,Dépenses!$J$6:$J$336,"2022",Dépenses!$I$6:$I$336,A11,Dépenses!$C$6:$C$336,$R$4) -> 0 | S11: =SUMIFS(Dépenses!$K$6:$K$336,Dépenses!$E$6:$E$336,$S$5,Dépenses!$J$6:$J$336,"2022",Dépenses!$I$6:$I$336,A11,Dépenses!$C$6:$C$336,$R$4) -> 0 | T11: =SUMIFS(Dépenses!$K$6:$K$336,Dépenses!$E$6:$E$336,$T$5,Dépenses!$J$6:$J$336,"2022",Dépenses!$I$6:$I$336,A11,Dépenses!$C$6:$C$336,$T$4) -> 0 | U11: =SUMIFS(Dépenses!$K$6:$K$336,Dépenses!$E$6:$E$336,$U$5,Dépenses!$J$6:$J$336,"2022",Dépenses!$I$6:$I$336,A11,Dépenses!$C$6:$C$336,$U$4) -> 850 | V11: =SUMIFS(Dépenses!$K$6:$K$336,Dépenses!$E$6:$E$336,$V$5,Dépenses!$J$6:$J$336,"2022",Dépenses!$I$6:$I$336,A11,Dépenses!$C$6:$C$336,$V$4) -> 95 | W11: =SUMIFS(Dépenses!$K$6:$K$336,Dépenses!$E$6:$E$336,$W$5,Dépenses!$J$6:$J$336,"2022",Dépenses!$I$6:$I$336,A11,Dépenses!$C$6:$C$336,$W$4) -> 0 | X11: =SUM(I11:W11) -> 13458.01
A12: 6 | B12: Juin | C12: ='2022'!D163 - SUMIFS(Transfert!J9:J83,Transfert!F9:F83,"2022",Transfert!G9:G83,A12) -> 17390 | D12: =SUMIFS(Recettes!$J$6:$J$68,Recettes!$D$6:$D$68,$D$5,Recettes!$I$6:$I$68,"2022",Recettes!$H$6:$H$68,A12) -> 0 | E12: =SUMIFS(Recettes!$J$6:$J$68,Recettes!$F$6:$F$68,$E$5,Recettes!$I$6:$I$68,"2022",Recettes!$H$6:$H$68,A12) + SUMIFS(Transfert!J9:J83,Transfert!I9:I83,$E$5,Transfert!F9:F83,"2022",Transfert!G9:G83,A12) -> 3690 | F12: =SUMIFS(Recettes!$J$6:$J$68,Recettes!$F$6:$F$68,$F$5,Recettes!$I$6:$I$68,"2022",Recettes!$H$6:$H$68,A12) + SUMIFS(Transfert!K9:K81,Transfert!J9:J83,$F$5,Transfert!G9:G83,"2022",Transfert!H9:H83,A12) -> #VALUE! | H12: Juin | I12: =SUMIFS(Dépenses!$K$6:$K$336,Dépenses!$E$6:$E$336,$I$5,Dépenses!$J$6:$J$336,"2022",Dépenses!$I$6:$I$336,A12,Dépenses!$C$6:$C$336,$I$4) -> 8700 | J12: =SUMIFS(Dépenses!$K$6:$K$336,Dépenses!$E$6:$E$336,$J$5,Dépenses!$J$6:$J$336,"2022",Dépenses!$I$6:$I$336,A12,Dépenses!$C$6:$C$336,$J$4) -> 2514.3 | K12: =SUMIFS(Dépenses!$K$6:$K$336,Dépenses!$C$6:$C$336,"Primes Annuelles - Aid El Fitr",Dépenses!$J$6:$J$336,"2022",Dépenses!$I$6:$I$336,A12) + SUMIFS(Dépenses!$K$6:$K$336,Dépenses!$C$6:$C$336,"Primes Annuelles - Aid Al Adha",Dépenses!$J$6:$J$336,"2022",Dépenses!$I$6:$I$336,A12) -> 3500 | L12: =SUMIFS(Dépenses!$K$6:$K$336,Dépenses!$E$6:$E$336,$L$5,Dépenses!$J$6:$J$336,"2022",Dépenses!$I$6:$I$336,A12,Dépenses!$C$6:$C$336,$L$4) -> 1146.65 | M12: =SUMIFS(Dépenses!$K$6:$K$336,Dépenses!$E$6:$E$336,$M$5,Dépenses!$J$6:$J$336,"2022",Dépenses!$I$6:$I$336,A12,Dépenses!$C$6:$C$336,$M$4) -> 199 | N12: =SUMIFS(Dépenses!$K$6:$K$336,Dépenses!$E$6:$E$336,$N$5,Dépenses!$J$6:$J$336,"2022",Dépenses!$I$6:$I$336,A12,Dépenses!$C$6:$C$336,$N$4) -> 100 | O12: =SUMIFS(Dépenses!$K$6:$K$336,Dépenses!$E$6:$E$336,$O$5,Dépenses!$J$6:$J$336,"2022",Dépenses!$I$6:$I$336,A12,Dépenses!$C$6:$C$336,$O$4) -> 333 | P12: =SUMIFS(Dépenses!$K$6:$K$336,Dépenses!$E$6:$E$336,$P$5,Dépenses!$J$6:$J$336,"2022",Dépenses!$I$6:$I$336,A12,Dépenses!$C$6:$C$336,$P$4) -> 0 | Q12: =SUMIFS(Dépenses!$K$6:$K$336,Dépenses!$E$6:$E$336,$Q$5,Dépenses!$J$6:$J$336,"2022",Dépenses!$I$6:$I$336,A12,Dépenses!$C$6:$C$336,$Q$4) -> 0 | R12: =SUMIFS(Dépenses!$K$6:$K$336,Dépenses!$E$6:$E$336,$R$5,Dépenses!$J$6:$J$336,"2022",Dépenses!$I$6:$I$336,A12,Dépenses!$C$6:$C$336,$R$4) -> 0 | S12: =SUMIFS(Dépenses!$K$6:$K$336,Dépenses!$E$6:$E$336,$S$5,Dépenses!$J$6:$J$336,"2022",Dépenses!$I$6:$I$336,A12,Dépenses!$C$6:$C$336,$R$4) -> 0 | T12: =SUMIFS(Dépenses!$K$6:$K$336,Dépenses!$E$6:$E$336,$T$5,Dépenses!$J$6:$J$336,"2022",Dépenses!$I$6:$I$336,A12,Dépenses!$C$6:$C$336,$T$4) -> 0 | U12: =SUMIFS(Dépenses!$K$6:$K$336,Dépenses!$E$6:$E$336,$U$5,Dépenses!$J$6:$J$336,"2022",Dépenses!$I$6:$I$336,A12,Dépenses!$C$6:$C$336,$U$4) -> 380 | V12: =SUMIFS(Dépenses!$K$6:$K$336,Dépenses!$E$6:$E$336,$V$5,Dépenses!$J$6:$J$336,"2022",Dépenses!$I$6:$I$336,A12,Dépenses!$C$6:$C$336,$V$4) -> 190 | W12: =SUMIFS(Dépenses!$K$6:$K$336,Dépenses!$E$6:$E$336,$W$5,Dépenses!$J$6:$J$336,"2022",Dépenses!$I$6:$I$336,A12,Dépenses!$C$6:$C$336,$W$4) -> 0 | X12: =SUM(I12:W12) -> 17062.95
A13: 7 | B13: Juillet | C13: ='2022'!D164 - SUMIFS(Transfert!J10:J84,Transfert!F10:F84,"2022",Transfert!G10:G84,A13) -> 13330 | D13: =SUMIFS(Recettes!$J$6:$J$68,Recettes!$D$6:$D$68,$D$5,Recettes!$I$6:$I$68,"2022",Recettes!$H$6:$H$68,A13) -> 1870 | E13: =SUMIFS(Recettes!$J$6:$J$68,Recettes!$F$6:$F$68,$E$5,Recettes!$I$6:$I$68,"2022",Recettes!$H$6:$H$68,A13) + SUMIFS(Transfert!J10:J84,Transfert!I10:I84,$E$5,Transfert!F10:F84,"2022",Transfert!G10:G84,A13) -> 3500 | F13: =SUMIFS(Recettes!$J$6:$J$68,Recettes!$F$6:$F$68,$F$5,Recettes!$I$6:$I$68,"2022",Recettes!$H$6:$H$68,A13) + SUMIFS(Transfert!K10:K81,Transfert!J10:J84,$F$5,Transfert!G10:G84,"2022",Transfert!H10:H84,A13) -> #VALUE! | H13: Juillet | I13: =SUMIFS(Dépenses!$K$6:$K$336,Dépenses!$E$6:$E$336,$I$5,Dépenses!$J$6:$J$336,"2022",Dépenses!$I$6:$I$336,A13,Dépenses!$C$6:$C$336,$I$4) -> 8810 | J13: =SUMIFS(Dépenses!$K$6:$K$336,Dépenses!$E$6:$E$336,$J$5,Dépenses!$J$6:$J$336,"2022",Dépenses!$I$6:$I$336,A13,Dépenses!$C$6:$C$336,$J$4) -> 2514.3 | K13: =SUMIFS(Dépenses!$K$6:$K$336,Dépenses!$C$6:$C$336,"Primes Annuelles - Aid El Fitr",Dépenses!$J$6:$J$336,"2022",Dépenses!$I$6:$I$336,A13) + SUMIFS(Dépenses!$K$6:$K$336,Dépenses!$C$6:$C$336,"Primes Annuelles - Aid Al Adha",Dépenses!$J$6:$J$336,"2022",Dépenses!$I$6:$I$336,A13) -> 0 | L13: =SUMIFS(Dépenses!$K$6:$K$336,Dépenses!$E$6:$E$336,$L$5,Dépenses!$J$6:$J$336,"2022",Dépenses!$I$6:$I$336,A13,Dépenses!$C$6:$C$336,$L$4) -> 1536.38 | M13: =SUMIFS(Dépenses!$K$6:$K$336,Dépenses!$E$6:$E$336,$M$5,Dépenses!$J$6:$J$336,"2022",Dépenses!$I$6:$I$336,A13,Dépenses!$C$6:$C$336,$M$4) -> 199 | N13: =SUMIFS(Dépenses!$K$6:$K$336,Dépenses!$E$6:$E$336,$N$5,Dépenses!$J$6:$J$336,"2022",Dépenses!$I$6:$I$336,A13,Dépenses!$C$6:$C$336,$N$4) -> 440 | O13: =SUMIFS(Dépenses!$K$6:$K$336,Dépenses!$E$6:$E$336,$O$5,Dépenses!$J$6:$J$336,"2022",Dépenses!$I$6:$I$336,A13,Dépenses!$C$6:$C$336,$O$4) -> 90 | P13: =SUMIFS(Dépenses!$K$6:$K$336,Dépenses!$E$6:$E$336,$P$5,Dépenses!$J$6:$J$336,"2022",Dépenses!$I$6:$I$336,A13,Dépenses!$C$6:$C$336,$P$4) -> 0 | Q13: =SUMIFS(Dépenses!$K$6:$K$336,Dépenses!$E$6:$E$336,$Q$5,Dépenses!$J$6:$J$336,"2022",Dépenses!$I$6:$I$336,A13,Dépenses!$C$6:$C$336,$Q$4) -> 0 | R13: =SUMIFS(Dépenses!$K$6:$K$336,Dépenses!$E$6:$E$336,$R$5,Dépenses!$J$6:$J$336,"2022",Dépenses!$I$6:$I$336,A13,Dépenses!$C$6:$C$336,$R$4) -> 0 | S13: =SUMIFS(Dépenses!$K$6:$K$336,Dépenses!$E$6:$E$336,$S$5,Dépenses!$J$6:$J$336,"2022",Dépenses!$I$6:$I$336,A13,Dépenses!$C$6:$C$336,$R$4) -> 0 | T13: =SUMIFS(Dépenses!$K$6:$K$336,Dépenses!$E$6:$E$336,$T$5,Dépenses!$J$6:$J$336,"2022",Dépenses!$I$6:$I$336,A13,Dépenses!$C$6:$C$336,$T$4) -> 0 | U13: =SUMIFS(Dépenses!$K$6:$K$336,Dépenses!$E$6:$E$336,$U$5,Dépenses!$J$6:$J$336,"2022",Dépenses!$I$6:$I$336,A13,Dépenses!$C$6:$C$336,$U$4) -> 835 | V13: =SUMIFS(Dépenses!$K$6:$K$336,Dépenses!$E$6:$E$336,$V$5,Dépenses!$J$6:$J$336,"2022",Dépenses!$I$6:$I$336,A13,Dépenses!$C$6:$C$336,$V$4) -> 71 | W13: =SUMIFS(Dépenses!$K$6:$K$336,Dépenses!$E$6:$E$336,$W$5,Dépenses!$J$6:$J$336,"2022",Dépenses!$I$6:$I$336,A13,Dépenses!$C$6:$C$336,$W$4) -> 0 | X13: =SUM(I13:W13) -> 14495.68
A14: 8 | B14: Août | C14: ='2022'!D165 - SUMIFS(Transfert!J11:J85,Transfert!F11:F85,"2022",Transfert!G11:G85,A14) -> 11030 | D14: =SUMIFS(Recettes!$J$6:$J$68,Recettes!$D$6:$D$68,$D$5,Recettes!$I$6:$I$68,"2022",Recettes!$H$6:$H$68,A14) -> 3929 | E14: =SUMIFS(Recettes!$J$6:$J$68,Recettes!$F$6:$F$68,$E$5,Recettes!$I$6:$I$68,"2022",Recettes!$H$6:$H$68,A14) + SUMIFS(Transfert!J11:J85,Transfert!I11:I85,$E$5,Transfert!F11:F85,"2022",Transfert!G11:G85,A14) -> 3500 | F14: =SUMIFS(Recettes!$J$6:$J$68,Recettes!$F$6:$F$68,$F$5,Recettes!$I$6:$I$68,"2022",Recettes!$H$6:$H$68,A14) + SUMIFS(Transfert!K11:K82,Transfert!J11:J85,$F$5,Transfert!G11:G85,"2022",Transfert!H11:H85,A14) -> #VALUE! | H14: Août | I14: =SUMIFS(Dépenses!$K$6:$K$336,Dépenses!$E$6:$E$336,$I$5,Dépenses!$J$6:$J$336,"2022",Dépenses!$I$6:$I$336,A14,Dépenses!$C$6:$C$336,$I$4) -> 8700 | J14: =SUMIFS(Dépenses!$K$6:$K$336,Dépenses!$E$6:$E$336,$J$5,Dépenses!$J$6:$J$336,"2022",Dépenses!$I$6:$I$336,A14,Dépenses!$C$6:$C$336,$J$4) -> 2514.3 | K14: =SUMIFS(Dépenses!$K$6:$K$336,Dépenses!$C$6:$C$336,"Primes Annuelles - Aid El Fitr",Dépenses!$J$6:$J$336,"2022",Dépenses!$I$6:$I$336,A14) + SUMIFS(Dépenses!$K$6:$K$336,Dépenses!$C$6:$C$336,"Primes Annuelles - Aid Al Adha",Dépenses!$J$6:$J$336,"2022",Dépenses!$I$6:$I$336,A14) -> 0 | L14: =SUMIFS(Dépenses!$K$6:$K$336,Dépenses!$E$6:$E$336,$L$5,Dépenses!$J$6:$J$336,"2022",Dépenses!$I$6:$I$336,A14,Dépenses!$C$6:$C$336,$L$4) -> 1209.92 | M14: =SUMIFS(Dépenses!$K$6:$K$336,Dépenses!$E$6:$E$336,$M$5,Dépenses!$J$6:$J$336,"2022",Dépenses!$I$6:$I$336,A14,Dépenses!$C$6:$C$336,$M$4) -> 199 | N14: =SUMIFS(Dépenses!$K$6:$K$336,Dépenses!$E$6:$E$336,$N$5,Dépenses!$J$6:$J$336,"2022",Dépenses!$I$6:$I$336,A14,Dépenses!$C$6:$C$336,$N$4) -> 105 | O14: =SUMIFS(Dépenses!$K$6:$K$336,Dépenses!$E$6:$E$336,$O$5,Dépenses!$J$6:$J$336,"2022",Dépenses!$I$6:$I$336,A14,Dépenses!$C$6:$C$336,$O$4) -> 100 | P14: =SUMIFS(Dépenses!$K$6:$K$336,Dépenses!$E$6:$E$336,$P$5,Dépenses!$J$6:$J$336,"2022",Dépenses!$I$6:$I$336,A14,Dépenses!$C$6:$C$336,$P$4) -> 0 | Q14: =SUMIFS(Dépenses!$K$6:$K$336,Dépenses!$E$6:$E$336,$Q$5,Dépenses!$J$6:$J$336,"2022",Dépenses!$I$6:$I$336,A14,Dépenses!$C$6:$C$336,$Q$4) -> 150 | R14: =SUMIFS(Dépenses!$K$6:$K$336,Dépenses!$E$6:$E$336,$R$5,Dépenses!$J$6:$J$336,"2022",Dépenses!$I$6:$I$336,A14,Dépenses!$C$6:$C$336,$R$4) -> 0 | S14: =SUMIFS(Dépenses!$K$6:$K$336,Dépenses!$E$6:$E$336,$S$5,Dépenses!$J$6:$J$336,"2022",Dépenses!$I$6:$I$336,A14,Dépenses!$C$6:$C$336,$R$4) -> 0 | T14: =SUMIFS(Dépenses!$K$6:$K$336,Dépenses!$E$6:$E$336,$T$5,Dépenses!$J$6:$J$336,"2022",Dépenses!$I$6:$I$336,A14,Dépenses!$C$6:$C$336,$T$4) -> 0 | U14: =SUMIFS(Dépenses!$K$6:$K$336,Dépenses!$E$6:$E$336,$U$5,Dépenses!$J$6:$J$336,"2022",Dépenses!$I$6:$I$336,A14,Dépenses!$C$6:$C$336,$U$4) -> 1420 | V14: =SUMIFS(Dépenses!$K$6:$K$336,Dépenses!$E$6:$E$336,$V$5,Dépenses!$J$6:$J$336,"2022",Dépenses!$I$6:$I$336,A14,Dépenses!$C$6:$C$336,$V$4) -> 287 | W14: =SUMIFS(Dépenses!$K$6:$K$336,Dépenses!$E$6:$E$336,$W$5,Dépenses!$J$6:$J$336,"2022",Dépenses!$I$6:$I$336,A14,Dépenses!$C$6:$C$336,$W$4) -> 0 | X14: =SUM(I14:W14) -> 14685.22
A15: 9 | B15: Sept | C15: ='2022'!D166 - SUMIFS(Transfert!J12:J86,Transfert!F12:F86,"2022",Transfert!G12:G86,A15) -> 13530 | D15: =SUMIFS(Recettes!$J$6:$J$68,Recettes!$D$6:$D$68,$D$5,Recettes!$I$6:$I$68,"2022",Recettes!$H$6:$H$68,A15) -> 5504 | E15: =SUMIFS(Recettes!$J$6:$J$68,Recettes!$F$6:$F$68,$E$5,Recettes!$I$6:$I$68,"2022",Recettes!$H$6:$H$68,A15) + SUMIFS(Transfert!J12:J86,Transfert!I12:I86,$E$5,Transfert!F12:F86,"2022",Transfert!G12:G86,A15) -> 3500 | F15: =SUMIFS(Recettes!$J$6:$J$68,Recettes!$F$6:$F$68,$F$5,Recettes!$I$6:$I$68,"2022",Recettes!$H$6:$H$68,A15) + SUMIFS(Transfert!K12:K83,Transfert!J12:J86,$F$5,Transfert!G12:G86,"2022",Transfert!H12:H86,A15) -> #VALUE! | H15: Sept | I15: =SUMIFS(Dépenses!$K$6:$K$336,Dépenses!$E$6:$E$336,$I$5,Dépenses!$J$6:$J$336,"2022",Dépenses!$I$6:$I$336,A15,Dépenses!$C$6:$C$336,$I$4) -> 9130 | J15: =SUMIFS(Dépenses!$K$6:$K$336,Dépenses!$E$6:$E$336,$J$5,Dépenses!$J$6:$J$336,"2022",Dépenses!$I$6:$I$336,A15,Dépenses!$C$6:$C$336,$J$4) -> 2514.3 | K15: =SUMIFS(Dépenses!$K$6:$K$336,Dépenses!$C$6:$C$336,"Primes Annuelles - Aid El Fitr",Dépenses!$J$6:$J$336,"2022",Dépenses!$I$6:$I$336,A15) + SUMIFS(Dépenses!$K$6:$K$336,Dépenses!$C$6:$C$336,"Primes Annuelles - Aid Al Adha",Dépenses!$J$6:$J$336,"2022",Dépenses!$I$6:$I$336,A15) -> 0 | L15: =SUMIFS(Dépenses!$K$6:$K$336,Dépenses!$E$6:$E$336,$L$5,Dépenses!$J$6:$J$336,"2022",Dépenses!$I$6:$I$336,A15,Dépenses!$C$6:$C$336,$L$4) -> 1169.59 | M15: =SUMIFS(Dépenses!$K$6:$K$336,Dépenses!$E$6:$E$336,$M$5,Dépenses!$J$6:$J$336,"2022",Dépenses!$I$6:$I$336,A15,Dépenses!$C$6:$C$336,$M$4) -> 199 | N15: =SUMIFS(Dépenses!$K$6:$K$336,Dépenses!$E$6:$E$336,$N$5,Dépenses!$J$6:$J$336,"2022",Dépenses!$I$6:$I$336,A15,Dépenses!$C$6:$C$336,$N$4) -> 380 | O15: =SUMIFS(Dépenses!$K$6:$K$336,Dépenses!$E$6:$E$336,$O$5,Dépenses!$J$6:$J$336,"2022",Dépenses!$I$6:$I$336,A15,Dépenses!$C$6:$C$336,$O$4) -> 75 | P15: =SUMIFS(Dépenses!$K$6:$K$336,Dépenses!$E$6:$E$336,$P$5,Dépenses!$J$6:$J$336,"2022",Dépenses!$I$6:$I$336,A15,Dépenses!$C$6:$C$336,$P$4) -> 0 | Q15: =SUMIFS(Dépenses!$K$6:$K$336,Dépenses!$E$6:$E$336,$Q$5,Dépenses!$J$6:$J$336,"2022",Dépenses!$I$6:$I$336,A15,Dépenses!$C$6:$C$336,$Q$4) -> 80 | R15: =SUMIFS(Dépenses!$K$6:$K$336,Dépenses!$E$6:$E$336,$R$5,Dépenses!$J$6:$J$336,"2022",Dépenses!$I$6:$I$336,A15,Dépenses!$C$6:$C$336,$R$4) -> 0 | S15: =SUMIFS(Dépenses!$K$6:$K$336,Dépenses!$E$6:$E$336,$S$5,Dépenses!$J$6:$J$336,"2022",Dépenses!$I$6:$I$336,A15,Dépenses!$C$6:$C$336,$R$4) -> 0 | T15: =SUMIFS(Dépenses!$K$6:$K$336,Dépenses!$E$6:$E$336,$T$5,Dépenses!$J$6:$J$336,"2022",Dépenses!$I$6:$I$336,A15,Dépenses!$C$6:$C$336,$T$4) -> 0 | U15: =SUMIFS(Dépenses!$K$6:$K$336,Dépenses!$E$6:$E$336,$U$5,Dépenses!$J$6:$J$336,"2022",Dépenses!$I$6:$I$336,A15,Dépenses!$C$6:$C$336,$U$4) -> 550 | V15: =SUMIFS(Dépenses!$K$6:$K$336,Dépenses!$E$6:$E$336,$V$5,Dépenses!$J$6:$J$336,"2022",Dépenses!$I$6:$I$336,A15,Dépenses!$C$6:$C$336,$V$4) -> 95 | W15: =SUMIFS(Dépenses!$K$6:$K$336,Dépenses!$E$6:$E$336,$W$5,Dépenses!$J$6:$J$336,"2022",Dépenses!$I$6:$I$336,A15,Dépenses!$C$6:$C$336,$W$4) -> 0 | X15: =SUM(I15:W15) -> 14192.89
A16: 10 | B16: Oct | C16: ='2022'!D167 - SUMIFS(Transfert!J13:J87,Transfert!F13:F87,"2022",Transfert!G13:G87,A16) -> 13930 | D16: =SUMIFS(Recettes!$J$6:$J$68,Recettes!$D$6:$D$68,$D$5,Recettes!$I$6:$I$68,"2022",Recettes!$H$6:$H$68,A16) -> 452 | E16: =SUMIFS(Recettes!$J$6:$J$68,Recettes!$F$6:$F$68,$E$5,Recettes!$I$6:$I$68,"2022",Recettes!$H$6:$H$68,A16) + SUMIFS(Transfert!J13:J87,Transfert!I13:I87,$E$5,Transfert!F13:F87,"2022",Transfert!G13:G87,A16) -> 3500 | F16: =SUMIFS(Recettes!$J$6:$J$68,Recettes!$F$6:$F$68,$F$5,Recettes!$I$6:$I$68,"2022",Recettes!$H$6:$H$68,A16) + SUMIFS(Transfert!K13:K84,Transfert!J13:J87,$F$5,Transfert!G13:G87,"2022",Transfert!H13:H87,A16) -> #VALUE! | H16: Oct | I16: =SUMIFS(Dépenses!$K$6:$K$336,Dépenses!$E$6:$E$336,$I$5,Dépenses!$J$6:$J$336,"2022",Dépenses!$I$6:$I$336,A16,Dépenses!$C$6:$C$336,$I$4) -> 9130 | J16: =SUMIFS(Dépenses!$K$6:$K$336,Dépenses!$E$6:$E$336,$J$5,Dépenses!$J$6:$J$336,"2022",Dépenses!$I$6:$I$336,A16,Dépenses!$C$6:$C$336,$J$4) -> 2514.3 | K16: =SUMIFS(Dépenses!$K$6:$K$336,Dépenses!$C$6:$C$336,"Primes Annuelles - Aid El Fitr",Dépenses!$J$6:$J$336,"2022",Dépenses!$I$6:$I$336,A16) + SUMIFS(Dépenses!$K$6:$K$336,Dépenses!$C$6:$C$336,"Primes Annuelles - Aid Al Adha",Dépenses!$J$6:$J$336,"2022",Dépenses!$I$6:$I$336,A16) -> 0 | L16: =SUMIFS(Dépenses!$K$6:$K$336,Dépenses!$E$6:$E$336,$L$5,Dépenses!$J$6:$J$336,"2022",Dépenses!$I$6:$I$336,A16,Dépenses!$C$6:$C$336,$L$4) -> 1244.27 | M16: =SUMIFS(Dépenses!$K$6:$K$336,Dépenses!$E$6:$E$336,$M$5,Dépenses!$J$6:$J$336,"2022",Dépenses!$I$6:$I$336,A16,Dépenses!$C$6:$C$336,$M$4) -> 199 | N16: =SUMIFS(Dépenses!$K$6:$K$336,Dépenses!$E$6:$E$336,$N$5,Dépenses!$J$6:$J$336,"2022",Dépenses!$I$6:$I$336,A16,Dépenses!$C$6:$C$336,$N$4) -> 180 | O16: =SUMIFS(Dépenses!$K$6:$K$336,Dépenses!$E$6:$E$336,$O$5,Dépenses!$J$6:$J$336,"2022",Dépenses!$I$6:$I$336,A16,Dépenses!$C$6:$C$336,$O$4) -> 129 | P16: =SUMIFS(Dépenses!$K$6:$K$336,Dépenses!$E$6:$E$336,$P$5,Dépenses!$J$6:$J$336,"2022",Dépenses!$I$6:$I$336,A16,Dépenses!$C$6:$C$336,$P$4) -> 0 | Q16: =SUMIFS(Dépenses!$K$6:$K$336,Dépenses!$E$6:$E$336,$Q$5,Dépenses!$J$6:$J$336,"2022",Dépenses!$I$6:$I$336,A16,Dépenses!$C$6:$C$336,$Q$4) -> 0 | R16: =SUMIFS(Dépenses!$K$6:$K$336,Dépenses!$E$6:$E$336,$R$5,Dépenses!$J$6:$J$336,"2022",Dépenses!$I$6:$I$336,A16,Dépenses!$C$6:$C$336,$R$4) -> 300 | S16: =SUMIFS(Dépenses!$K$6:$K$336,Dépenses!$E$6:$E$336,$S$5,Dépenses!$J$6:$J$336,"2022",Dépenses!$I$6:$I$336,A16,Dépenses!$C$6:$C$336,$R$4) -> 21960 | T16: =SUMIFS(Dépenses!$K$6:$K$336,Dépenses!$E$6:$E$336,$T$5,Dépenses!$J$6:$J$336,"2022",Dépenses!$I$6:$I$336,A16,Dépenses!$C$6:$C$336,$T$4) -> 200 | U16: =SUMIFS(Dépenses!$K$6:$K$336,Dépenses!$E$6:$E$336,$U$5,Dépenses!$J$6:$J$336,"2022",Dépenses!$I$6:$I$336,A16,Dépenses!$C$6:$C$336,$U$4) -> 400 | V16: =SUMIFS(Dépenses!$K$6:$K$336,Dépenses!$E$6:$E$336,$V$5,Dépenses!$J$6:$J$336,"2022",Dépenses!$I$6:$I$336,A16,Dépenses!$C$6:$C$336,$V$4) -> 95 | W16: =SUMIFS(Dépenses!$K$6:$K$336,Dépenses!$E$6:$E$336,$W$5,Dépenses!$J$6:$J$336,"2022",Dépenses!$I$6:$I$336,A16,Dépenses!$C$6:$C$336,$W$4) -> 0 | X16: =SUM(I16:W16) -> 36351.57
A17: 11 | B17: Nov | C17: ='2022'!D168 - SUMIFS(Transfert!J14:J88,Transfert!F14:F88,"2022",Transfert!G14:G88,A17) -> 10900 | D17: =SUMIFS(Recettes!$J$6:$J$68,Recettes!$D$6:$D$68,$D$5,Recettes!$I$6:$I$68,"2022",Recettes!$H$6:$H$68,A17) -> 368 | E17: =SUMIFS(Recettes!$J$6:$J$68,Recettes!$F$6:$F$68,$E$5,Recettes!$I$6:$I$68,"2022",Recettes!$H$6:$H$68,A17) + SUMIFS(Transfert!J14:J88,Transfert!I14:I88,$E$5,Transfert!F14:F88,"2022",Transfert!G14:G88,A17) -> 3500 | F17: =SUMIFS(Recettes!$J$6:$J$68,Recettes!$F$6:$F$68,$F$5,Recettes!$I$6:$I$68,"2022",Recettes!$H$6:$H$68,A17) + SUMIFS(Transfert!K14:K85,Transfert!J14:J88,$F$5,Transfert!G14:G88,"2022",Transfert!H14:H88,A17) -> #VALUE! | H17: Nov | I17: =SUMIFS(Dépenses!$K$6:$K$336,Dépenses!$E$6:$E$336,$I$5,Dépenses!$J$6:$J$336,"2022",Dépenses!$I$6:$I$336,A17,Dépenses!$C$6:$C$336,$I$4) -> 9130 | J17: =SUMIFS(Dépenses!$K$6:$K$336,Dépenses!$E$6:$E$336,$J$5,Dépenses!$J$6:$J$336,"2022",Dépenses!$I$6:$I$336,A17,Dépenses!$C$6:$C$336,$J$4) -> 2640.01 | K17: =SUMIFS(Dépenses!$K$6:$K$336,Dépenses!$C$6:$C$336,"Primes Annuelles - Aid El Fitr",Dépenses!$J$6:$J$336,"2022",Dépenses!$I$6:$I$336,A17) + SUMIFS(Dépenses!$K$6:$K$336,Dépenses!$C$6:$C$336,"Primes Annuelles - Aid Al Adha",Dépenses!$J$6:$J$336,"2022",Dépenses!$I$6:$I$336,A17) -> 0 | L17: =SUMIFS(Dépenses!$K$6:$K$336,Dépenses!$E$6:$E$336,$L$5,Dépenses!$J$6:$J$336,"2022",Dépenses!$I$6:$I$336,A17,Dépenses!$C$6:$C$336,$L$4) -> 950.98 | M17: =SUMIFS(Dépenses!$K$6:$K$336,Dépenses!$E$6:$E$336,$M$5,Dépenses!$J$6:$J$336,"2022",Dépenses!$I$6:$I$336,A17,Dépenses!$C$6:$C$336,$M$4) -> 199 | N17: =SUMIFS(Dépenses!$K$6:$K$336,Dépenses!$E$6:$E$336,$N$5,Dépenses!$J$6:$J$336,"2022",Dépenses!$I$6:$I$336,A17,Dépenses!$C$6:$C$336,$N$4) -> 0 | O17: =SUMIFS(Dépenses!$K$6:$K$336,Dépenses!$E$6:$E$336,$O$5,Dépenses!$J$6:$J$336,"2022",Dépenses!$I$6:$I$336,A17,Dépenses!$C$6:$C$336,$O$4) -> 80 | P17: =SUMIFS(Dépenses!$K$6:$K$336,Dépenses!$E$6:$E$336,$P$5,Dépenses!$J$6:$J$336,"2022",Dépenses!$I$6:$I$336,A17,Dépenses!$C$6:$C$336,$P$4) -> 0 | Q17: =SUMIFS(Dépenses!$K$6:$K$336,Dépenses!$E$6:$E$336,$Q$5,Dépenses!$J$6:$J$336,"2022",Dépenses!$I$6:$I$336,A17,Dépenses!$C$6:$C$336,$Q$4) -> 0 | R17: =SUMIFS(Dépenses!$K$6:$K$336,Dépenses!$E$6:$E$336,$R$5,Dépenses!$J$6:$J$336,"2022",Dépenses!$I$6:$I$336,A17,Dépenses!$C$6:$C$336,$R$4) -> 0 | S17: =SUMIFS(Dépenses!$K$6:$K$336,Dépenses!$E$6:$E$336,$S$5,Dépenses!$J$6:$J$336,"2022",Dépenses!$I$6:$I$336,A17,Dépenses!$C$6:$C$336,$R$4) -> 0 | T17: =SUMIFS(Dépenses!$K$6:$K$336,Dépenses!$E$6:$E$336,$T$5,Dépenses!$J$6:$J$336,"2022",Dépenses!$I$6:$I$336,A17,Dépenses!$C$6:$C$336,$T$4) -> 0 | U17: =SUMIFS(Dépenses!$K$6:$K$336,Dépenses!$E$6:$E$336,$U$5,Dépenses!$J$6:$J$336,"2022",Dépenses!$I$6:$I$336,A17,Dépenses!$C$6:$C$336,$U$4) -> 0 | V17: =SUMIFS(Dépenses!$K$6:$K$336,Dépenses!$E$6:$E$336,$V$5,Dépenses!$J$6:$J$336,"2022",Dépenses!$I$6:$I$336,A17,Dépenses!$C$6:$C$336,$V$4) -> 95 | W17: =SUMIFS(Dépenses!$K$6:$K$336,Dépenses!$E$6:$E$336,$W$5,Dépenses!$J$6:$J$336,"2022",Dépenses!$I$6:$I$336,A17,Dépenses!$C$6:$C$336,$W$4) -> 0 | X17: =SUM(I17:W17) -> 13094.99
A18: 12 | B18: Déc | C18: ='2022'!D169 - SUMIFS(Transfert!J15:J89,Transfert!F15:F89,"2022",Transfert!G15:G89,A18) -> 17629 | D18: =SUMIFS(Recettes!$J$6:$J$68,Recettes!$D$6:$D$68,$D$5,Recettes!$I$6:$I$68,"2022",Recettes!$H$6:$H$68,A18) -> 2274 | E18: =SUMIFS(Recettes!$J$6:$J$68,Recettes!$F$6:$F$68,$E$5,Recettes!$I$6:$I$68,"2022",Recettes!$H$6:$H$68,A18) + SUMIFS(Transfert!J15:J89,Transfert!I15:I89,$E$5,Transfert!F15:F89,"2022",Transfert!G15:G89,A18) -> 3500 | F18: =SUMIFS(Recettes!$J$6:$J$68,Recettes!$F$6:$F$68,$F$5,Recettes!$I$6:$I$68,"2022",Recettes!$H$6:$H$68,A18) + SUMIFS(Transfert!K15:K86,Transfert!J15:J89,$F$5,Transfert!G15:G89,"2022",Transfert!H15:H89,A18) -> #VALUE! | H18: Déc | I18: =SUMIFS(Dépenses!$K$6:$K$336,Dépenses!$E$6:$E$336,$I$5,Dépenses!$J$6:$J$336,"2022",Dépenses!$I$6:$I$336,A18,Dépenses!$C$6:$C$336,$I$4) -> 9130 | J18: =SUMIFS(Dépenses!$K$6:$K$336,Dépenses!$E$6:$E$336,$J$5,Dépenses!$J$6:$J$336,"2022",Dépenses!$I$6:$I$336,A18,Dépenses!$C$6:$C$336,$J$4) -> 2640.01 | K18: =SUMIFS(Dépenses!$K$6:$K$336,Dépenses!$C$6:$C$336,"Primes Annuelles - Aid El Fitr",Dépenses!$J$6:$J$336,"2022",Dépenses!$I$6:$I$336,A18) + SUMIFS(Dépenses!$K$6:$K$336,Dépenses!$C$6:$C$336,"Primes Annuelles - Aid Al Adha",Dépenses!$J$6:$J$336,"2022",Dépenses!$I$6:$I$336,A18) -> 0 | L18: =SUMIFS(Dépenses!$K$6:$K$336,Dépenses!$E$6:$E$336,$L$5,Dépenses!$J$6:$J$336,"2022",Dépenses!$I$6:$I$336,A18,Dépenses!$C$6:$C$336,$L$4) -> 891.4 | M18: =SUMIFS(Dépenses!$K$6:$K$336,Dépenses!$E$6:$E$336,$M$5,Dépenses!$J$6:$J$336,"2022",Dépenses!$I$6:$I$336,A18,Dépenses!$C$6:$C$336,$M$4) -> 199 | N18: =SUMIFS(Dépenses!$K$6:$K$336,Dépenses!$E$6:$E$336,$N$5,Dépenses!$J$6:$J$336,"2022",Dépenses!$I$6:$I$336,A18,Dépenses!$C$6:$C$336,$N$4) -> 250 | O18: =SUMIFS(Dépenses!$K$6:$K$336,Dépenses!$E$6:$E$336,$O$5,Dépenses!$J$6:$J$336,"2022",Dépenses!$I$6:$I$336,A18,Dépenses!$C$6:$C$336,$O$4) -> 0 | P18: =SUMIFS(Dépenses!$K$6:$K$336,Dépenses!$E$6:$E$336,$P$5,Dépenses!$J$6:$J$336,"2022",Dépenses!$I$6:$I$336,A18,Dépenses!$C$6:$C$336,$P$4) -> 0 | Q18: =SUMIFS(Dépenses!$K$6:$K$336,Dépenses!$E$6:$E$336,$Q$5,Dépenses!$J$6:$J$336,"2022",Dépenses!$I$6:$I$336,A18,Dépenses!$C$6:$C$336,$Q$4) -> 0 | R18: =SUMIFS(Dépenses!$K$6:$K$336,Dépenses!$E$6:$E$336,$R$5,Dépenses!$J$6:$J$336,"2022",Dépenses!$I$6:$I$336,A18,Dépenses!$C$6:$C$336,$R$4) -> 0 | S18: =SUMIFS(Dépenses!$K$6:$K$336,Dépenses!$E$6:$E$336,$S$5,Dépenses!$J$6:$J$336,"2022",Dépenses!$I$6:$I$336,A18,Dépenses!$C$6:$C$336,$R$4) -> 0 | T18: =SUMIFS(Dépenses!$K$6:$K$336,Dépenses!$E$6:$E$336,$T$5,Dépenses!$J$6:$J$336,"2022",Dépenses!$I$6:$I$336,A18,Dépenses!$C$6:$C$336,$T$4) -> 0 | U18: =SUMIFS(Dépenses!$K$6:$K$336,Dépenses!$E$6:$E$336,$U$5,Dépenses!$J$6:$J$336,"2022",Dépenses!$I$6:$I$336,A18,Dépenses!$C$6:$C$336,$U$4) -> 800 | V18: =SUMIFS(Dépenses!$K$6:$K$336,Dépenses!$E$6:$E$336,$V$5,Dépenses!$J$6:$J$336,"2022",Dépenses!$I$6:$I$336,A18,Dépenses!$C$6:$C$336,$V$4) -> 95 | W18: =SUMIFS(Dépenses!$K$6:$K$336,Dépenses!$E$6:$E$336,$W$5,Dépenses!$J$6:$J$336,"2022",Dépenses!$I$6:$I$336,A18,Dépenses!$C$6:$C$336,$W$4) -> 0 | X18: =SUM(I18:W18) -> 14005.41
B19: TOTAL | C19: =SUM(C7:C18) -> 157919 | D19: =SUM(D7:D18) -> 22837 | E19: =SUM(E7:E18) -> 65280 | F19: =SUM(F7:F18) -> #VALUE! | G19: =+D19+#REF!+#REF!+F19 -> #REF! | H19: TOTAL | I19: =SUM(I7:I18) -> 107150 | J19: =SUM(J7:J18) -> 27280.14 | K19: =SUM(K7:K18) -> 4700 | L19: =SUM(L7:L18) -> 12287.75 | M19: =SUM(M7:M18) -> 2388 | N19: =SUM(N7:N18) -> 2154 | O19: =SUM(O7:O18) -> 1076 | P19: =SUM(P7:P18) -> 1000 | ... W19: =SUM(W7:W18) -> 32804 | X19: =SUM(I19:W19) -> 221798.89
B20: SOLDE 2022 | G20: =+G6+G19 -> #REF! | X20: =+X6+X19 -> 221798.89
B21: RECETTES -DEPENSES 2019-2020-2021 : (154394,00)-(102322,00) = | X21: =+G20-X20 -> #REF!
